Workbook

Sheet Instructions_Disclaimer
M7: © 2014
B8: LM5066I Design Tool- Rev. C
B10: Typical design procedure
B11: Typical applications require multiple passes through the design tool using MOSFET factors such as transient
B12: thermal response and safe operating area curves. Refer to the following application reports for more detail.
B14: Robust Hot Swap Design
B15: LM5066I Datasheet (See "Applications and Implementation")
B17: The basic design process follows:
B18: 1. Enter operating conditions.
B19: 2. Select current limit parameters.
B20: 3. Enter MOSTFET SOA characteristics & power limit.
B21: 4. Select start up conditions (load and/or soft start). Check whether FET is operating with reasonable margin, within the SOA curve.
B22: If not, try changing start-up conditions (soft start values, timer values), add more FETs in parallel, or switch to FET with better SOA.
... B36: TEXAS INSTRUMENTS TEXT FILE LICENSE Copyright (c) 2014 Texas Instruments Incorporated All rights reserved not granted herein. Limited License. Texas Instruments Incorporated grants a world-wide, royalty-free, non-exclusive license under copyrights and patents it now or hereafter owns or controls to make, have made, use, import, offer to sell and sell ("Utilize") this software subject to the terms herein. With respect to the foregoing patent license, such license is granted solely to the extent that any such patent is necessary to Utilize the software alone. The patent license shall not apply to any combinations which include this software, other than combinations with devices manufactured by or for TI (“TI Devices”). No hardware patent is licensed hereunder. Redistributions must preserve existing copyright notices and reproduce this license (including the above copyright notice and the disclaimer and (if applicable) source code license limitations below) in the documentation and/or other materials provided with the distribution Redistribution and use in binary form, without modification, are permitted provided that the following conditions are met: * No reverse engineering, decompilation, or disassembly of this software is permitted with respect to any software provided in binary form. * any redistribution and use are licensed by TI for use only with TI Devices. * Nothing shall obligate TI to provide you with source code for the software licensed and provided to you in object code. If software source code is provided to you, modification and redistribution of the source code are permitted provided that the following conditions are met: * any redistribution and use of the source code, including any resulting derivative works, are licensed by TI for use only with TI Devices. * any redistribution and use of any object code compiled from the source code and any resulting derivative works, are licensed by TI for use only with TI Devices. Neither the name of Texas Instruments Incorporated nor the names of its suppliers may be used to endorse or promote products derived from this software without specific prior written permission. DISCLAIMER. THIS SOFTWARE IS PROVIDED BY TI AND TI’S LICENSORS "AS IS" AND ANY EXPRESS OR IMPLIED WARRANTIES, INCLUDING, BUT NOT LIMITED TO, THE IMPLIED WARRANTIES OF MERCHANTABILITY AND FITNESS FOR A PARTICULAR PURPOSE ARE DISCLAIMED. IN NO EVENT SHALL TI AND TI’S LICENSORS BE LIABLE FOR ANY DIRECT, INDIRECT, INCIDENTAL, SPECIAL, EXEMPLARY, OR CONSEQUENTIAL DAMAGES (INCLUDING, BUT NOT LIMITED TO, PROCUREMENT OF SUBSTITUTE GOODS OR SERVICES; LOSS OF USE, DATA, OR PROFITS; OR BUSINESS INTERRUPTION) HOWEVER CAUSED AND ON ANY THEORY OF LIABILITY, WHETHER IN CONTRACT, STRICT LIABILITY, OR TORT (INCLUDING NEGLIGENCE OR OTHERWISE) ARISING IN ANY WAY OUT OF THE USE OF THIS SOFTWARE, EVEN IF ADVISED OF THE POSSIBILITY OF SUCH DAMAGE.

Sheet Design Calculator
A1: LM5066I PMBus Hot Swap Design Tool
B2: www.ti.com/hotswap
D9: Enter Values in Green Shaded Cells
D10: Calculated Values are shown in White Cells
D11: Yellow and Red cells highlight potential issues with the design. Red highlights items that are higher risk.
B14: Step 0: Calculator Tutorials | D14: Note: Before proceeding, please watch the video tutorials listed to ensure accurate results from this tool! | AU14: Yes
AU15: No
D16: Steps 1 & 2: Operating Conditions, Current Limit, & Circuit Breaker (7:41)
D17: Step 3: MOSFET Selection (9:58)
D18: Step 4: Startup (10:32)
D19: Step 5: UVLO, OVLO & PGD Thresholds (4:20)
D20: LM5066I Datasheet
D22: I understand and agree to watch the video tutorials if help is needed. (Choose Yes to enable the calculator.) | G22: Yes
D23: Assure to follow the layout and application guidelines listed on the datasheet. | G23: Yes
D24: *For additional questions not addressed in the videos, please post on E2E.ti.com
B27: Step 1: Operating Conditions | E27: Minimum Input Operating Voltage: VIN(MIN) | F27: 10 | G27: V
E28: Nominal Input Operating Voltage: VIN(NOM) | F28: 48 | G28: V
E29: Maximum Input Operating Voltage: VIN(MAX) | F29: 50 | G29: V
E30: Maximum Load Current: IOUT(MAX) | F30: 78 | G30: A
E31: Maximum Output Load Capacitance: CLOAD | F31: 4000 | G31: µF
E32: Maximum Ambient Operating Temperature: TMAX | F32: 85 | G32: oC
B33: Steps 1 & 2: Operating Conditions, Current Limit, & Circuit Breaker
B38: Step 2: Current Limit and Circuit Breaker | E38: Current Limit Range (CL) | F38: 26 mV | AN38: 26 mV
E39: Maximum Recommended Value for Effective Sense Resistance | F39: =Equations!F9 -> 0.2970297 | G39: mW | AN39: 50 mV
E40: Use External Resistor Divider to Reduce Effecitve RS | F40: No | AN40: Yes
E41: Enter the Resistance for RS | F41: 0.3 | G41: mW | AN41: No
E42: Recommended Value for RCL1 | F42: =Equations!F10 -> 10 | G42: W
E43: Recommended Value for RCL2 | F43: =Equations!F11 -> 0 | G43: W
E44: Enter value for RCL1 | F44: 10 | G44: W | AN44: =AND(F40="No") -> 1
B45: Steps 1 & 2: Operating Conditions, Current Limit, & Circuit Breaker | E45: Enter value for RCL2 | F45: 3.04 | G45: W
E46: Effective Sense Resistance (RS,EFF) | F46: =RsEFF -> 0.3 | G46: mW
E47: Resulting Minimum Current Limit | F47: =CLMIN -> 78 | G47: A
E48: Resulting Typical Current Limit | F48: =CLNOM -> 86.666667 | G48: A
E49: Resulting Maximum Current Limit | F49: =CLMAX -> 95.333333 | G49: A | AN49: Retry
E50: Maximum Power Dissipation in RS | F50: =Equations!F16/1000 -> 2.7265333 | G50: W | AN50: Latch Off
E51: Fault Response | F51: Retry | AN51: 1.9 x Current Limit
E52: Circuit Breaker to Current Limit Raitio | F52: 1.9 x Current Limit | AN52: 3.9 x Current Limit
B53: Step 3: MOSFET Selection | E53: Q1 FET Name | F53: PSMN4R8-100BSE | AP53: # FETS | AQ53: 3
E54: Estimated MOSFET RQJA | F54: =40/AQ53 -> 13.333333 | G54: oC/W | AN54: =((((TJMAX-TAMB)/ThetaJA)/(CLMAX^2))*1000)*NUMFETS^2 -> 3.0120666 | AO54: =((TJMAX-TAMB)/ThetaJA) -> 27.375
E55: Number of MosFETs | F55: 1 | G55: # | AN55: Values Used
E56: MOSFET On resistance @ TJ,DC | F56: =9.6/AQ53 -> 3.2 | G56: mW | AN56: =F56 -> 3.2
E57: Maximum FET Junction Temperature | F57: 450 | G57: oC | AN57: =F57 -> 450
E58: 100ms SOA Current (re-use 1ms data if unavailable) @ VIN(MAX) | F58: =100*AQ53 -> 300 | G58: A | AN58: =F58 -> 300
E59: 1ms SOA Current @ VIN(MAX) | F59: =27*AQ53 -> 81 | G59: A | AN59: =F59 -> 81
B60: Step 3: MOSFET Selection | E60: 10ms SOA Current @ VIN(MAX) | F60: =6*AQ53 -> 18 | G60: A | AN60: =F60 -> 18
E61: 100ms Current at @ VIN(MAX) (enter 'NA' if not available) | F61: =2.1*AQ53 -> 6.3 | G61: A | AN61: =F61 -> 6.3
E62: 1s or DC SOA Current at @ VIN(MAX) (enter 'NA' if not available) | F62: =1.5*AQ53 -> 4.5 | G62: A | AN62: =F62 -> 4.5
B63: Note: TI recommends choosing a FET with SOA current specified for 100ms and/or 1s or DC. If choosing a FET without these parameters, this calculator will estimate the values via extrapolation, which leaves an inherent associated risk. | E63: FET Power dissapation at full load (per FET) | F63: =(IOUTMAX/NUMFETS)^2*RDSON/1000 -> 19.4688 | G63: W
E64: Maximum steady state FET Junction Temperature (TJ,DC) | F64: =TAMB+(FETPDISS*ThetaJA) -> 344.584 | G64: oC
E65: Minimum Power Limit to Ensure Vsns > 4mV (PLIM,MIN) | F65: =Equations!F29 -> 666.66667 | G65: W
E66: Target Power Limit | F66: 700 | G66: W
E67: Calculated RPWR | F67: =Equations!F31 -> 23.857143 | G67: kW
E68: Actual RPWR | F68: 24 | G68: kW | I68: Note: Hover here to see the 3 values affecting this curve, consult a thermal expert if you are unsure!
E69: Actual PLIM | F69: =Equations!F33 -> 703.33333 | G69: W
B70: Step 4: Startup | E70: Load Turn-On Threshold | F70: 0 | G70: V
E71: Startup Load Type | F71: Constant Current
E72: Startup Load Value | F72: 0 | G72: =IF(F71="Constant Current","A","Ohms") -> A | AN72: Constant Current
E73: Use External Soft-Start Control (dv/dt) | F73: Yes | AN73: Resistive
E74: Typical Start Time with Vinmax (Tstart) | F74: =Start_up!M2 -> 32.5 | G74: ms
E75: IFET - ILOAD margin (lowest for Vout range) | F75: =Start_up!O2 -> 1
E76: Target Fault Timer: Tstart + Margin | F76: =Equations!F46 -> 48.75 | G76: ms
E77: Target Timer capacitance | F77: =Equations!F47 -> 937.5 | G77: nF
E78: Selected Timer capacitance | F78: 20000 | G78: nF
B79: Step 4: Startup | E79: Final Fault Timer(Tfault) | F79: =Equations!F49 -> 1040 | G79: ms
E80: Derated SOA / PLIM | F80: =Equations!F50 -> 2.0715824
E81: Can a "hot" board be hotplugged | F81: No
E82: Recommended slew Rate (max) | F82: =dv_dt_recommendations!J28 -> 2.4648433 | G82: V/ms
E83: Recommended slew Rate (min) | F83: =dv_dt_recommendations!J29 -> 0.1070856 | G83: V/ms
E84: dv/dt rate on Vout | F84: 1.5 | G84: V/ms
E85: calculated SS capacitance | F85: =Equations!F53 -> 13.333333 | G85: nF
B86: Note: This is the typical dv/dt rate, but max value can be 2x. This is because the gate source current can vary from 20uA to 40uA. Thus TI recommends keeping the overall SOA margin during start-up >1.5 in order to compensate for this. | E86: actual SS capacitance | F86: 13 | G86: nF
E87: actual typical dv/dt rate on Vout | F87: =Equations!F55 -> 1.5384615 | G87: V/ms
E88: SOA margin during start-up | F88: =Equations!F62 -> 2.0221258
E89: Target Fault Time | F89: 0.25 | G89: ms
E90: Calculated Timer Capacitance | F90: =Equations!F67 -> 4.8076923 | G90: nF
E91: Actual Timer Capacitance ( pick one smaller than CT,CALC) | F91: 10 | G91: nF
E92: Actual Fault Time (Tfault) | F92: =Equations!F69 -> 0.52 | G92: ms
E93: SOA margin during "hot-short" or "start-into short" | F93: =Equations!F71 -> 2.0715824
E94: Resulting Typical Insertion Delay Time | F94: =Equations!F98 -> 8.125 | G94: ms
E95: Resulting Typical Restart Time | F95: =Equations!F101 -> 82.877143 | G95: ms
B96: Step 5: UVLO, OVLO & PGD Thresholds | E96: Select Option A or Option B | F96: Option B | AN96: Option A
E97: Desired Upper UVLO Threshold | F97: 38 | G97: V | AN97: Option B
E98: Desired Lower UVLO Threshold | F98: 35 | G98: V | AN98: Option C
E99: Desired Upper OVLO Threshold | F99: 65 | G99: V | AN99: Option D
E100: Desired Lower OVLO Threshold | F100: 63 | G100: V
E101: Recommended Resistance for: R1 | F101: =IF(F96="Option A",Equations!F119,Equations!G119) -> 150 | G101: kW
E102: R2 | F102: =IF(F96="Option A",Equations!F120,Equations!G120) -> 11.439114 | G102: kW
B103: Step 5: UVLO, OVLO & PGD Thresholds | E103: R3 | F103: =IF(F96="Option A",Equations!F121,Equations!G121) -> 95.238095 | G103: kW
E104: R4 | F104: =IF(F96="Option A",Equations!F122,Equations!G122) -> 3.7461739 | G104: kW
E105: Enter the Resistance for R1 | F105: 150 | G105: kW
E106: Enter the Resistance for R2 | F106: 11.5 | G106: kW
E107: Enter the Resistance for R3 | F107: 95.3 | G107: kW
E108: Enter the Resistance for R4 | F108: 3.74 | G108: kW
C110: Resulting Thresholds: | D110: Minimum | E110: Typical | F110: Maximum
C111: Resulting Upper UVLO Threshold = | D111: =IF($F$96="Option A",Equations!F123,Equations!G123) -> 36.244783 | E111: =IF($F$96="Option A",Equations!F124,Equations!G124) -> 37.827826 | F111: =IF($F$96="Option A",Equations!F125,Equations!G125) -> 39.41087 | G111: V
C112: Resulting Lower UVLO Threshold = | D112: =IF($F$96="Option A",Equations!F126,Equations!G126) -> 33.844783 | E112: =IF($F$96="Option A",Equations!F127,Equations!G127) -> 34.827826 | F112: =IF($F$96="Option A",Equations!F128,Equations!G128) -> 35.81087 | G112: V
C113: Resulting Upper OVLO Threshold = | D113: =IF($F$96="Option A",Equations!F129,Equations!G129) -> 63.290267 | E113: =IF($F$96="Option A",Equations!F130,Equations!G130) -> 65.143957 | F113: =IF($F$96="Option A",Equations!F131,Equations!G131) -> 66.997647 | G113: V
C114: Resulting Lower OVLO Threshold = | D114: =IF($F$96="Option A",Equations!F132,Equations!G132) -> 61.003067 | E114: =IF($F$96="Option A",Equations!F133,Equations!G133) -> 63.142657 | F114: =IF($F$96="Option A",Equations!F134,Equations!G134) -> 65.472847 | G114: V
C115: Note: If any of the cells above are yellow, then these values are outside of the device's operating range. This will result in the device turning either on or off at its operating limits rather than at the user selected values in yellow.
E118: Enter the Resistance for RPG | F118: 100 | G118: kW
...

Sheet Device Parameters
C2: Min | D2: Typ | E2: Max | F2: Units
A3: Operating Conditions
B4: Junction Temperature | C4: -40 | E4: 125
B5: Input Voltage | C5: 10 | E5: 80 | F5: V
A6: Current Limit
B7: Threshold Voltage CL = VDD | C7: 23.4 | D7: 26 | E7: 28.6
B8: Threshold Voltage CL = GND | C8: 45 | D8: 50 | E8: 55
B9: Sense input Current | C9: 20 | D9: 25 | E9: 35 | F9: uA
A11: Power Limit
B12: Systematic Offset | E12: 0.001 | F12: V
B13: Minimum Recommended Vsns | E13: 0.004 | F13: V | G13: <= I am assuming this would have +/- 50% error at best
B14: A_coeff | E14: =1/(0.000007) -> 142857.14
B16: Key Equations: | C16: Vsns = Rpwr / (A*Vds) + Vos,syst | I16: Example: | J16: Vds | K16: Rpwr | L16: Rsns (m-ohm) | M16: Plim | N16: Vsns (mV) | P16: Plim | Q16: Rpwr
C17: Plim (Vds) = 1/Rs * [ Rpwr/A + Vds * Vos, syst= | J17: 12 | K17: 25 | L17: =0.5 -> 0.5 | M17: =1/(0.001*L17)*(K17*1000/$E$14+J17*$E$12) -> 374 | N17: =K17*1000/$E$14/J17+$E$12 -> 0.015583333 | P17: 82 | Q17: =E14*(P17*L17*0.001-J17*E12) -> 4142.8571
C18: Rpwr = A * [PLIM(Vds) * Rs - 0.043] | J18: 12 | K18: 5 | L18: =0.5 -> 0.5 | M18: =1/(0.001*L18)*(K18*1000/$E$14+J18*$E$12) -> 94 | N18: =K18*1000/$E$14/J18+$E$12*0.001 -> 0.0029176667
B19: How Plim varries vs Vds: | I19: Ex: Plim @ 13V = 100W, Rs = 0.5; Plim @ (Vds = 5V) = 100W - 7V * 1mV/0.5mili-ohm = 100W - 14W = 86W
A21: Timer
B22: Upper Threshold | C22: 3.74 | D22: 3.9 | E22: 4.07 | F22: V
B23: Insertion Time Current | C23: -5.9 | D23: -4.8 | E23: -3.3 | F23: uA
B24: timer_constant
B25: Fault detection current | C25: 90 | D25: 75 | E25: 60 | F25: uA
B26: Computed Start - Up Slop | D26: =SQRT(0.66^2+ ((120-90)/90)^2+ 0.1^2) -> 0.74613076 | G26: <= mean root square(T_start_error_Plim, timer_error, cap_error); T_start proportional to 1/Plim => T_start_error_plim = 1/(1-Plim_err) - 1 = 1/(1-0.4) - 1 = 0.66
B27: Slop for calculations | D27: 0.5 | G27: Note: We get additional buffer, b/c this is designed for a Vinmax, while typically Vin = Vinnom
A29: Gate
B30: Gate Sourcing Current | C30: 7.5 | D30: 20 | E30: 40
A32: Circuit Breaker | C32: 26mV | F32: 50mV
B33: 1.9 x Threshold | C33: 38 | D33: 48 | E33: 58 | F33: 76 | G33: 96 | H33: 116
B34: 1.9x CB:CL Ratio | C34: 1.5 | D34: 1.88 | E34: 2.3 | F34: 1.64 | G34: 1.94 | H34: 2.23
B35: 3.9 x Threshold | C35: 76 | D35: 96 | E35: 116 | F35: 155 | G35: 193 | H35: 235
B36: 3.9x CB:CL Ratio | C36: 3.1 | D36: 3.75 | E36: 4.45 | F36: 3.28 | G36: 3.87 | H36: 4.45
A38: Timer Pin
B39: Upper Threshold | C39: 3.74 | D39: 3.9 | E39: 4.07
B40: Lower Threshold (Restart) | C40: 1 | D40: 1.2 | E40: 1.4
B41: End of Cycle | D41: 0.3
B42: Re-enable threshold | D42: 0.3
B43: Insertion time current | C43: 3.3 | D43: 4.8 | E43: 5.9
B44: Sink current, end of insertion | C44: 0.9 | D44: 1.5 | E44: 2.1
B45: Fault detection current | C45: 60 | D45: 75 | E45: 90
B46: Fault sink current | C46: 1.7 | D46: 2.8 | E46: 3.2
A48: Power Good
B49: PGVOL | D49: 100 | E49: 400 | F49: mV | G49: 2 | H49: mA sinking
A50: FB Pin
B51: FB Threshold | C51: 2.41 | D51: 2.46 | E51: 2.52 | F51: V
B52: FB Hysteresis Current | C52: 15 | D52: 20 | E52: 25 | F52: uA

Sheet Equations
A2: Current Limit
D4: CLMIN = | E4: =IF('Design Calculator'!$F$38="26 mV",'Device Parameters'!C7,'Device Parameters'!C8) -> 23.4 | F4: mV
D5: CLNOM = | E5: =IF('Design Calculator'!$F$38="26 mV",'Device Parameters'!D7,'Device Parameters'!D8) -> 26 | F5: mV
D6: CLMAX = | E6: =IF('Design Calculator'!$F$38="26 mV",'Device Parameters'!E7,'Device Parameters'!E8) -> 28.6 | F6: mV
E9: Max Rs = | F9: =CLMIN_Threshold/('Design Calculator'!F30*1.01) -> 0.2970297
E10: RCL1 Recommended = | F10: =IF(Rs>RsMAX,10,"NA") -> 10
E11: RCL2 Recommmended = | F11: =IF(Rs>RsMAX,(((IOUTMAX*Rs)/CLMIN_Threshold)-1)*F10,"NA") -> 0
E12: Effective Rs = | F12: =IF(RsMAX>Rs,Rs,IF('Design Calculator'!F40="Yes",IF(Rs>RsMAX,Rs/(1+RDIV2/RDIV1),Rs),Rs)) -> 0.3
E13: Min. Current limit = | F13: =CLMIN_Threshold/RsEFF -> 78
E14: Typ. Current limit = | F14: =CLNOM_Threshold/RsEFF -> 86.666667
E15: Max. Current limit = | F15: =CLMAX_Threshold/RsEFF -> 95.333333
E16: Rs Power Diss. = | F16: =F15^2*'Design Calculator'!F41 -> 2726.5333
E19: CB threshold: | F19: =CLNOM_Threshold*IF('Design Calculator'!F52 = "1.9 x Current Limit", 1.9, 3.9) -> 49.4 | G19: mV
E20: CB threshold | F20: =F19/RsEFF -> 164.66667 | G20: A
A22: FET Selection
F23: Nominal | H23: Derated at TJ
E24: 100ms SOA Current Maximum Input Voltage | F24: =VINMAX*'Design Calculator'!F58 -> 15000 | G24: W | H24: =F24*(TJMAX-TJ)/(TJMAX-25) -> 3720.5647
E25: 1ms SOA Current Maximum Input Voltage | F25: =VINMAX*'Design Calculator'!F59 -> 4050 | G25: W | H25: =F25*(TJMAX-TJ)/(TJMAX-25) -> 1004.5525
E26: 10ms SOA Current Maximum Input Voltage | F26: =VINMAX*'Design Calculator'!F60 -> 900 | G26: W | H26: =F26*(TJMAX-TJ)/(TJMAX-25) -> 223.23388
E27: 100ms or DC SOA Current at Maximum Input Voltage | F27: =VINMAX*'Design Calculator'!F61 -> 315 | G27: W | H27: =F27*(TJMAX-TJ)/(TJMAX-25) -> 78.131859
E29: Minimum Power Limit= | F29: =VINMAX*'Device Parameters'!E13/RsEFF/0.001 -> 666.66667 | G29: W
E30: Target PLIM | F30: ='Design Calculator'!F66 -> 700 | G30: W
E31: Rpwr | F31: ='Device Parameters'!E14*(F30*RsEFF*0.001-0.043)/1000 -> 23.857143 | G31: k-ohm
E32: Rpwr actual | F32: =RPWR -> 24 | G32: k-ohm
E33: Final Plim | F33: =1/RsEFF*1000*(Equations!F32*1000/'Device Parameters'!E14+0.043) -> 703.33333 | G33: W
E37: Resulting Typical Power Limit = | F37: =F38*(1-0.24) -> 534.53333 | G37: 24% tolerance used in this calculation.
E38: Resulting Minimum Power Limit = | F38: =F33 -> 703.33333
E39: Resulting Maximum Power Limit = | F39: =F38*(1+0.24) -> 872.13333
A42: Startup
D43: With PLIM
E44: Typical Start time | F44: =Start_up!M2 -> 32.5 | G44: ms
E45: Start-slop | F45: ='Device Parameters'!D27 -> 0.5
E46: Target Fault Timer | F46: =F44*(1+F45) -> 48.75 | G46: ms
E47: Target Timer capacitance | F47: ='Device Parameters'!D25/'Device Parameters'!D22*F46 -> 937.5 | G47: nF
E48: Selected Timer capacitance | F48: ='Design Calculator'!F78 -> 20000 | G48: nF
E49: Final Fault Timer | F49: ='Device Parameters'!D22/'Device Parameters'!D25*F48 -> 1040 | G49: ms
E50: SOA / PLIM | F50: =SOA!C26/F38 -> 2.0715824
D51: With SS
E52: dv/dt rate | F52: ='Design Calculator'!F84 -> 1.5 | G52: V/ms
E53: calculated SS capacitance | F53: ='Device Parameters'!D30/ss_rate -> 13.333333 | G53: nF
E54: actual SS capacitance | F54: ='Design Calculator'!F86 -> 13 | G54: nF
E55: actual dv/dt rate | F55: =ss_rate*F53/F54 -> 1.5384615 | G55: V/ms
E56: I_Cout | F56: =COUTMAX*F55/1000 -> 6.1538462 | G56: A
E57: typical start time | F57: =VINMAX/F55 -> 32.5 | G57: ms
E58: FET Energy dissipated at start-up (EFET) | F58: =Start_up!N5 -> 4.9519231 | G58: J
E59: Peak Power dissipated during start-up (PFET) | F59: =Start_up!Q4 -> 307.69231 | G59: W
E60: Equivalent time at peak power - EFET/PFET (t_power) | F60: =F58/F59*1000 -> 16.09375 | G60: ms
E61: Available SOA for t_power at Vinmax | F61: =SOA!H28 -> 622.19254 | G61: W
E62: SOA margin | F62: =F61/F59 -> 2.0221258
F64: 1 | G64: ms
D65: Covering hot-short, start-into short for SS
E66: Target Fault Time | F66: ='Design Calculator'!F89 -> 0.25
E67: Calculated Timer Capacitance | F67: ='Device Parameters'!D25/'Device Parameters'!D22*F66 -> 4.8076923 | G67: nF
E68: Actual Timer Capacitance | F68: ='Design Calculator'!F91 -> 10 | G68: nF
E69: Actual Fault Time (Tfault) | F69: ='Device Parameters'!D22/'Device Parameters'!D25*F68 -> 0.52 | G69: ms
E70: Available derated SOA for Tfault | F70: =SOA!C26 -> 1457.013 | G70: W
E71: SOA margin | F71: =F70/F33 -> 2.0715824
G88: 10% margin added in this calculation
I91: UVLO upper is F40 | L91: R1 is F48
G92: A
G93: V/S
G94: nF
E97: Min Insertion time = | F97: =IF('Design Calculator'!F73="YES", Equations!F68, Equations!F48)*'Device Parameters'!C39*1000/'Device Parameters'!E43*0.001 -> 6.3389831 | G97: ms
E98: Typ. Insertion time = | F98: =IF('Design Calculator'!F73="YES", Equations!F68, Equations!F48)*0.001*'Device Parameters'!D39*1000/'Device Parameters'!D43 -> 8.125 | G98: ms
E99: Max Insertion time = | F99: =IF('Design Calculator'!F73="YES", Equations!F68, Equations!F48)*0.001*'Device Parameters'!E39*1000/'Device Parameters'!C43 -> 12.333333 | G99: ms
E100: Min Restart time = | F100: =IF('Design Calculator'!F73="YES", Equations!F68, Equations!F48)*(H100+I100+J100) -> 82.605714 | G100: ms | H100: =(('Device Parameters'!C39-'Device Parameters'!E40)/'Device Parameters'!E45)*7 -> 0.182 | I100: =(('Device Parameters'!C39-'Device Parameters'!C40)/'Device Parameters'!D46)*8 -> 7.8285714 | J100: =(('Device Parameters'!C40-'Device Parameters'!D41)/'Device Parameters'!D46) -> 0.25
E101: Typ. Restart time = | F101: =IF('Design Calculator'!F73="YES", Equations!F68, Equations!F48)*(H101+I101+J101) -> 82.877143 | G101: ms | H101: =(('Device Parameters'!D39-'Device Parameters'!D40)/'Device Parameters'!D45)*7 -> 0.252 | I101: =(('Device Parameters'!D39-'Device Parameters'!D40)/'Device Parameters'!D46)*8 -> 7.7142857 | J101: =(('Device Parameters'!D40-'Device Parameters'!D41)/'Device Parameters'!D46) -> 0.32142857
E102: Max Restart time = | F102: =IF('Design Calculator'!F73="YES", Equations!F68, Equations!F48)*(H102+I102+J102) -> 83.795952 | G102: ms | H102: =(('Device Parameters'!E39-'Device Parameters'!C40)/'Device Parameters'!C45)*7 -> 0.35816667 | I102: =(('Device Parameters'!E39-'Device Parameters'!E40)/'Device Parameters'!D46)*8 -> 7.6285714 | J102: =(('Device Parameters'!E40-'Device Parameters'!D41)/'Device Parameters'!D46) -> 0.39285714
E103: Min PG Threshold = | F103: =(1+'Design Calculator'!F123/'Design Calculator'!F124)*'Device Parameters'!C51 -> 36.838571
E104: Nom PG Threshold = | F104: =(1+'Design Calculator'!F123/'Design Calculator'!F124)*'Device Parameters'!D51 -> 37.602857
E105: Max PG Threshold = | F105: =(1+'Design Calculator'!F123/'Design Calculator'!F124)*'Device Parameters'!E51 -> 38.52
E106: Min PG Hysteresis = | F106: =('Design Calculator'!F123*'Device Parameters'!C52) -> 2250
E107: Nom PG Hysteresis = | F107: =('Design Calculator'!F123*'Device Parameters'!$D$52) -> 3000
E108: Max PG Hysteresis = | F108: =('Design Calculator'!F123*'Device Parameters'!$E$52) -> 3750
I111: UVLO lower is F41 | L111: R2 is F49
I112: OVLO upper is F42 | L112: R3 is F50
I113: OVLO lower is F43 | L113: R4 is F51
E116: Option A
E117: Option B
F118: A | G118: B | H118: C | I118: D
E119: R1 = | F119: =('Design Calculator'!F97-'Design Calculator'!F98)*1000/20 -> 150 | G119: =('Design Calculator'!F97-'Design Calculator'!F98)*1000/20 -> 150
E120: R2 = | F120: =2.48*F119/('Design Calculator'!F98-2.48)-F121 -> 5.3292648 | G120: =2.48*G119/('Design Calculator'!F98-2.48) -> 11.439114
E121: R3 = | F121: =(F119*'Design Calculator'!F98*2.46)/('Design Calculator'!F99*('Design Calculator'!F98-2.48)) -> 6.1098496 | G121: =('Design Calculator'!F99-'Design Calculator'!F100)*1000/21 -> 95.238095
E122: R4 = | G122: =2.46*G121/('Design Calculator'!F99-2.46) -> 3.7461739
E123: Resulting upper UVLO Threshold (min) = | F123: =2.41+('Design Calculator'!F105*((2.41/('Design Calculator'!F106+'Design Calculator'!F107))+(16/1000))) -> 8.1948315 | G123: =2.41+('Design Calculator'!F$105*((2.41/'Design Calculator'!F$106)+(16/1000))) -> 36.244783
E124: Resulting upper UVLO Threshold (typ) = | F124: =2.48+('Design Calculator'!F105*((2.48/('Design Calculator'!F106+'Design Calculator'!F107))+(20/1000))) -> 8.9631461 | G124: =2.48+('Design Calculator'!F$105*((2.48/'Design Calculator'!F$106)+(20/1000))) -> 37.827826
E125: Resulting upper UVLO Threshold (max) = | F125: =2.55+('Design Calculator'!F105*((2.55/('Design Calculator'!F106+'Design Calculator'!F107))+(24/1000))) -> 9.7314607 | G125: =2.55+('Design Calculator'!F$105*((2.55/'Design Calculator'!F$106)+(24/1000))) -> 39.41087
E126: Resulting lower UVLO Threshold (min) = | F126: =2.41*('Design Calculator'!F105+'Design Calculator'!F106+'Design Calculator'!F107)/('Design Calculator'!F106+'Design Calculator'!F107) -> 5.7948315 | G126: =2.41*('Design Calculator'!F$105+'Design Calculator'!F$106)/'Design Calculator'!F$106 -> 33.844783
E127: Resulting lower UVLO Threshold (typ) = | F127: =2.48*('Design Calculator'!F105+'Design Calculator'!F106+'Design Calculator'!F107)/('Design Calculator'!F106+'Design Calculator'!F107) -> 5.9631461 | G127: =2.48*('Design Calculator'!F$105+'Design Calculator'!F$106)/'Design Calculator'!F$106 -> 34.827826
E128: Resulting lower UVLO Threshold (max) = | F128: =2.55*('Design Calculator'!F105+'Design Calculator'!F106+'Design Calculator'!F107)/('Design Calculator'!F106+'Design Calculator'!F107) -> 6.1314607 | G128: =2.55*('Design Calculator'!F$105+'Design Calculator'!F$106)/'Design Calculator'!F$106 -> 35.81087
E129: Resulting upper OVLO Threshold (min) = | F129: =2.39*('Design Calculator'!F105+'Design Calculator'!F106+'Design Calculator'!F107)/'Design Calculator'!F107 -> 6.4402099 | G129: =2.39*('Design Calculator'!F$107+'Design Calculator'!F$108)/'Design Calculator'!F$108 -> 63.290267
E130: Resulting upper OVLO Threshold (typ) = | F130: =2.46*('Design Calculator'!F$105+'Design Calculator'!F$106+'Design Calculator'!F$107)/'Design Calculator'!F$107 -> 6.6288353 | G130: =2.46*('Design Calculator'!F$107+'Design Calculator'!F$108)/'Design Calculator'!F$108 -> 65.143957
E131: Resulting upper OVLO Threshold (max) = | F131: =2.53*('Design Calculator'!F$105+'Design Calculator'!F$106+'Design Calculator'!F$107)/'Design Calculator'!F$107 -> 6.8174607 | G131: =2.53*('Design Calculator'!F$107+'Design Calculator'!F$108)/'Design Calculator'!F$108 -> 66.997647
E132: Resulting lower OVLO Threshold (min) = | F132: =2.39+(('Design Calculator'!F$105+'Design Calculator'!F$106)*((2.39/'Design Calculator'!F$107)-(24/1000))) -> 2.5642099 | G132: =2.39+('Design Calculator'!F$107*((2.39/'Design Calculator'!F$108)-(24/1000))) -> 61.003067
E133: Resulting lower OVLO Threshold (typ) = | F133: =2.46+(('Design Calculator'!F$105+'Design Calculator'!F$106)*((2.46/'Design Calculator'!F$107)-(21/1000))) -> 3.2373353 | G133: =2.46+('Design Calculator'!F$107*((2.46/'Design Calculator'!F$108)-(21/1000))) -> 63.142657
E134: Resulting lower OVLO Threshold (max) = | F134: =2.53+(('Design Calculator'!F$105+'Design Calculator'!F$106)*((2.53/'Design Calculator'!F$107)-(16/1000))) -> 4.2334607 | G134: =2.53+('Design Calculator'!F$107*((2.53/'Design Calculator'!F$108)-(16/1000))) -> 65.472847
E142: Ramp time for output voltage | F142: ='design calculator'!#ref! -> #VALUE! | G142: ms
E143: Nominal output voltage | F143: ='Design Calculator'!F28 -> 48 | G143: V
E144: Required soft-start capacitance | F144: =22/F143*F142 -> #VALUE! | G144: nF
C165: GRAPH:
...

Sheet Start_up
B1: PLIM | C1: ILIM | D1: Load type | F1: SS | G1: Load Value | H1: Load start | I1: Rs | J1: Vos,syst | M1: Start-time | O1: I_fet-I_L margin | Q1: I_g(hi/nom) | R1: I_g(low/nom)
B2: ='Design Calculator'!F69 -> 703.33333 | C2: ='Design Calculator'!F48 -> 86.666667 | D2: =IF( 'Design Calculator'!F71 = "Constant Current", "CC", "R") -> CC | F2: ='Design Calculator'!F73 -> Yes | G2: ='Design Calculator'!F72 -> 0 | H2: ='Design Calculator'!F70 -> 0 | I2: =RsEFF -> 0.3 | J2: ='Device Parameters'!E12 -> 0.001 | M2: =J114*1000 -> 32.5 | N2: ms | O2: =MIN(L10:L111) -> 1 | Q2: ='Device Parameters'!E30/'Device Parameters'!D30 -> 2 | R2: ='Device Parameters'!C30/'Device Parameters'!D30 -> 0.375
D4: To avoid timer running: Iload + Icap,ss < IFET_PLIM / 2 => SS_RATE < 1/Cout * (IFET_PLIM/2 - ILOAD) | M4: Max_SS_Rate | N4: =MIN(M10:M114) -> 1.7583333 | O4: V/ms | P4: max_power_typ | Q4: =MAX(O10:O114) -> 307.69231 | R4: W
M5: FET_ENERGY | N5: =SUM(N10:N114) -> 4.9519231 | O5: J | P5: max_power_high | Q5: =MAX(P10:P114) -> 615.38462 | R5: W
P6: max_power_low | Q6: =MAX(Q10:Q114) -> 115.38462 | R6: W
A7: VIN | B7: Vout | C7: ILOAD | D7: PLIM | E7: IFET_PLIM | F7: I_FET_SS | G7: IFET | H7: ICAP | I7: Dt | J7: Time | K7: Tiime (ms) | L7: I_Fet-IL margin | M7: Max _allowed SS_rate | N7: FET_Energy | O7: Power (W) | P7: P_ fast_SS | Q7: P_slow_SS
K8: -1 | O8: 0
K9: -0.01 | O9: 0
A10: =VINMAX -> 50 | B10: =VINMAX*((ROW()-10)/104) -> 0 | C10: =IF(B10>=$H$2,IF($D$2="CC", $G$2, B10/$G$2), 0) -> 0 | D10: =B2 -> 703.33333 | E10: =MIN(D10/(A10-B10),$C$2) -> 14.066667 | F10: =I_Cout_ss+C10 -> 6.1538462 | G10: =IF($F$2="YES", F10, E10) -> 6.1538462 | H10: =G10-C10 -> 6.1538462 | I10: =(COUTMAX/1000000)*(B10)/H10 -> 0 | J10: =I10 -> 0 | K10: =J10*1000 -> 0 | L10: =H10/G10 -> 1 | M10: =1/COUTMAX*(E10/2-C10)*1000 -> 1.7583333 | N10: =I10*G10*(A10-B10) -> 0 | O10: =G10*(A10-B10) -> 307.69231 | P10: =(A10-B10)*(I_Cout_ss*$Q$2+C10) -> 615.38462 | Q10: =(A10-B10)*(I_Cout_ss*$R$2+C10) -> 115.38462
A11: =VINMAX -> 50 | B11: =VINMAX*((ROW()-10)/104) -> 0.48076923 | C11: =IF(B11>=$H$2,IF($D$2="CC", $G$2, B11/$G$2), 0) -> 0 | D11: =B2 -> 703.33333 | E11: =MIN(D11/(A11-B11),$C$2) -> 14.203236 | F11: =I_Cout_ss+C11 -> 6.1538462 | G11: =IF($F$2="YES", F11, E11) -> 6.1538462 | H11: =G11-C11 -> 6.1538462 | I11: =(COUTMAX/1000000)*(B11-B10)/H11 -> 0.0003125 | J11: =J10+I11 -> 0.0003125 | K11: =J11*1000 -> 0.3125 | L11: =H11/G11 -> 1 | M11: =1/COUTMAX*(E11/2-C11)*1000 -> 1.7754045 | N11: =I11*G11*(A11-B11) -> 0.09522929 | O11: =G11*(A11-B11) -> 304.73373 | P11: =(A11-B11)*(I_Cout_ss*$Q$2+C11) -> 609.46746 | Q11: =(A11-B11)*(I_Cout_ss*$R$2+C11) -> 114.27515
A12: =VINMAX -> 50 | B12: =VINMAX*((ROW()-10)/104) -> 0.96153846 | C12: =IF(B12>=$H$2,IF($D$2="CC", $G$2, B12/$G$2), 0) -> 0 | D12: =B2 -> 703.33333 | E12: =MIN(D12/(A12-B12),$C$2) -> 14.342484 | F12: =I_Cout_ss+C12 -> 6.1538462 | G12: =IF($F$2="YES", F12, E12) -> 6.1538462 | H12: =G12-C12 -> 6.1538462 | I12: =(COUTMAX/1000000)*(B12-B11)/H12 -> 0.0003125 | J12: =J11+I12 -> 0.000625 | K12: =J12*1000 -> 0.625 | L12: =H12/G12 -> 1 | M12: =1/COUTMAX*(E12/2-C12)*1000 -> 1.7928105 | N12: =I12*G12*(A12-B12) -> 0.094304734 | O12: =G12*(A12-B12) -> 301.77515 | P12: =(A12-B12)*(I_Cout_ss*$Q$2+C12) -> 603.5503 | Q12: =(A12-B12)*(I_Cout_ss*$R$2+C12) -> 113.16568 | X12: Start-up slop
A13: =VINMAX -> 50 | B13: =VINMAX*((ROW()-10)/104) -> 1.4423077 | C13: =IF(B13>=$H$2,IF($D$2="CC", $G$2, B13/$G$2), 0) -> 0 | D13: =B2 -> 703.33333 | E13: =MIN(D13/(A13-B13),$C$2) -> 14.484488 | F13: =I_Cout_ss+C13 -> 6.1538462 | G13: =IF($F$2="YES", F13, E13) -> 6.1538462 | H13: =G13-C13 -> 6.1538462 | I13: =(COUTMAX/1000000)*(B13-B12)/H13 -> 0.0003125 | J13: =J12+I13 -> 0.0009375 | K13: =J13*1000 -> 0.9375 | L13: =H13/G13 -> 1 | M13: =1/COUTMAX*(E13/2-C13)*1000 -> 1.8105611 | N13: =I13*G13*(A13-B13) -> 0.093380178 | O13: =G13*(A13-B13) -> 298.81657 | P13: =(A13-B13)*(I_Cout_ss*$Q$2+C13) -> 597.63314 | Q13: =(A13-B13)*(I_Cout_ss*$R$2+C13) -> 112.05621 | X13: QG | Y13: 0.3
A14: =VINMAX -> 50 | B14: =VINMAX*((ROW()-10)/104) -> 1.9230769 | C14: =IF(B14>=$H$2,IF($D$2="CC", $G$2, B14/$G$2), 0) -> 0 | D14: =B2 -> 703.33333 | E14: =MIN(D14/(A14-B14),$C$2) -> 14.629333 | F14: =I_Cout_ss+C14 -> 6.1538462 | G14: =IF($F$2="YES", F14, E14) -> 6.1538462 | H14: =G14-C14 -> 6.1538462 | I14: =(COUTMAX/1000000)*(B14-B13)/H14 -> 0.0003125 | J14: =J13+I14 -> 0.00125 | K14: =J14*1000 -> 1.25 | L14: =H14/G14 -> 1 | M14: =1/COUTMAX*(E14/2-C14)*1000 -> 1.8286667 | N14: =I14*G14*(A14-B14) -> 0.092455621 | O14: =G14*(A14-B14) -> 295.85799 | P14: =(A14-B14)*(I_Cout_ss*$Q$2+C14) -> 591.71598 | Q14: =(A14-B14)*(I_Cout_ss*$R$2+C14) -> 110.94675 | X14: I_Src | Y14: 0.3
A15: =VINMAX -> 50 | B15: =VINMAX*((ROW()-10)/104) -> 2.4038462 | C15: =IF(B15>=$H$2,IF($D$2="CC", $G$2, B15/$G$2), 0) -> 0 | D15: =B2 -> 703.33333 | E15: =MIN(D15/(A15-B15),$C$2) -> 14.777104 | F15: =I_Cout_ss+C15 -> 6.1538462 | G15: =IF($F$2="YES", F15, E15) -> 6.1538462 | H15: =G15-C15 -> 6.1538462 | I15: =(COUTMAX/1000000)*(B15-B14)/H15 -> 0.0003125 | J15: =J14+I15 -> 0.0015625 | K15: =J15*1000 -> 1.5625 | L15: =H15/G15 -> 1 | M15: =1/COUTMAX*(E15/2-C15)*1000 -> 1.847138 | N15: =I15*G15*(A15-B15) -> 0.091531065 | O15: =G15*(A15-B15) -> 292.89941 | P15: =(A15-B15)*(I_Cout_ss*$Q$2+C15) -> 585.79882 | Q15: =(A15-B15)*(I_Cout_ss*$R$2+C15) -> 109.83728 | X15: RMS | Y15: =SQRT(Y14^2+Y13^2) -> 0.42426407
A16: =VINMAX -> 50 | B16: =VINMAX*((ROW()-10)/104) -> 2.8846154 | C16: =IF(B16>=$H$2,IF($D$2="CC", $G$2, B16/$G$2), 0) -> 0 | D16: =B2 -> 703.33333 | E16: =MIN(D16/(A16-B16),$C$2) -> 14.927891 | F16: =I_Cout_ss+C16 -> 6.1538462 | G16: =IF($F$2="YES", F16, E16) -> 6.1538462 | H16: =G16-C16 -> 6.1538462 | I16: =(COUTMAX/1000000)*(B16-B15)/H16 -> 0.0003125 | J16: =J15+I16 -> 0.001875 | K16: =J16*1000 -> 1.875 | L16: =H16/G16 -> 1 | M16: =1/COUTMAX*(E16/2-C16)*1000 -> 1.8659864 | N16: =I16*G16*(A16-B16) -> 0.090606509 | O16: =G16*(A16-B16) -> 289.94083 | P16: =(A16-B16)*(I_Cout_ss*$Q$2+C16) -> 579.88166 | Q16: =(A16-B16)*(I_Cout_ss*$R$2+C16) -> 108.72781
A17: =VINMAX -> 50 | B17: =VINMAX*((ROW()-10)/104) -> 3.3653846 | C17: =IF(B17>=$H$2,IF($D$2="CC", $G$2, B17/$G$2), 0) -> 0 | D17: =B2 -> 703.33333 | E17: =MIN(D17/(A17-B17),$C$2) -> 15.081787 | F17: =I_Cout_ss+C17 -> 6.1538462 | G17: =IF($F$2="YES", F17, E17) -> 6.1538462 | H17: =G17-C17 -> 6.1538462 | I17: =(COUTMAX/1000000)*(B17-B16)/H17 -> 0.0003125 | J17: =J16+I17 -> 0.0021875 | K17: =J17*1000 -> 2.1875 | L17: =H17/G17 -> 1 | M17: =1/COUTMAX*(E17/2-C17)*1000 -> 1.8852234 | N17: =I17*G17*(A17-B17) -> 0.089681953 | O17: =G17*(A17-B17) -> 286.98225 | P17: =(A17-B17)*(I_Cout_ss*$Q$2+C17) -> 573.9645 | Q17: =(A17-B17)*(I_Cout_ss*$R$2+C17) -> 107.61834 | X17: PLIM | Y17: 0.3
A18: =VINMAX -> 50 | B18: =VINMAX*((ROW()-10)/104) -> 3.8461538 | C18: =IF(B18>=$H$2,IF($D$2="CC", $G$2, B18/$G$2), 0) -> 0 | D18: =B2 -> 703.33333 | E18: =MIN(D18/(A18-B18),$C$2) -> 15.238889 | F18: =I_Cout_ss+C18 -> 6.1538462 | G18: =IF($F$2="YES", F18, E18) -> 6.1538462 | H18: =G18-C18 -> 6.1538462 | I18: =(COUTMAX/1000000)*(B18-B17)/H18 -> 0.0003125 | J18: =J17+I18 -> 0.0025 | K18: =J18*1000 -> 2.5 | L18: =H18/G18 -> 1 | M18: =1/COUTMAX*(E18/2-C18)*1000 -> 1.9048611 | N18: =I18*G18*(A18-B18) -> 0.088757396 | O18: =G18*(A18-B18) -> 284.02367 | P18: =(A18-B18)*(I_Cout_ss*$Q$2+C18) -> 568.04734 | Q18: =(A18-B18)*(I_Cout_ss*$R$2+C18) -> 106.50888 | X18: combined | Y18: =MAX(Y15:Y17) -> 0.42426407
A19: =VINMAX -> 50 | B19: =VINMAX*((ROW()-10)/104) -> 4.3269231 | C19: =IF(B19>=$H$2,IF($D$2="CC", $G$2, B19/$G$2), 0) -> 0 | D19: =B2 -> 703.33333 | E19: =MIN(D19/(A19-B19),$C$2) -> 15.399298 | F19: =I_Cout_ss+C19 -> 6.1538462 | G19: =IF($F$2="YES", F19, E19) -> 6.1538462 | H19: =G19-C19 -> 6.1538462 | I19: =(COUTMAX/1000000)*(B19-B18)/H19 -> 0.0003125 | J19: =J18+I19 -> 0.0028125 | K19: =J19*1000 -> 2.8125 | L19: =H19/G19 -> 1 | M19: =1/COUTMAX*(E19/2-C19)*1000 -> 1.9249123 | N19: =I19*G19*(A19-B19) -> 0.08783284 | O19: =G19*(A19-B19) -> 281.06509 | P19: =(A19-B19)*(I_Cout_ss*$Q$2+C19) -> 562.13018 | Q19: =(A19-B19)*(I_Cout_ss*$R$2+C19) -> 105.39941
A20: =VINMAX -> 50 | B20: =VINMAX*((ROW()-10)/104) -> 4.8076923 | C20: =IF(B20>=$H$2,IF($D$2="CC", $G$2, B20/$G$2), 0) -> 0 | D20: =B2 -> 703.33333 | E20: =MIN(D20/(A20-B20),$C$2) -> 15.563121 | F20: =I_Cout_ss+C20 -> 6.1538462 | G20: =IF($F$2="YES", F20, E20) -> 6.1538462 | H20: =G20-C20 -> 6.1538462 | I20: =(COUTMAX/1000000)*(B20-B19)/H20 -> 0.0003125 | J20: =J19+I20 -> 0.003125 | K20: =J20*1000 -> 3.125 | L20: =H20/G20 -> 1 | M20: =1/COUTMAX*(E20/2-C20)*1000 -> 1.9453901 | N20: =I20*G20*(A20-B20) -> 0.086908284 | O20: =G20*(A20-B20) -> 278.10651 | P20: =(A20-B20)*(I_Cout_ss*$Q$2+C20) -> 556.21302 | Q20: =(A20-B20)*(I_Cout_ss*$R$2+C20) -> 104.28994 | X20: I_timer | Y20: 0.2
A21: =VINMAX -> 50 | B21: =VINMAX*((ROW()-10)/104) -> 5.2884615 | C21: =IF(B21>=$H$2,IF($D$2="CC", $G$2, B21/$G$2), 0) -> 0 | D21: =B2 -> 703.33333 | E21: =MIN(D21/(A21-B21),$C$2) -> 15.730466 | F21: =I_Cout_ss+C21 -> 6.1538462 | G21: =IF($F$2="YES", F21, E21) -> 6.1538462 | H21: =G21-C21 -> 6.1538462 | I21: =(COUTMAX/1000000)*(B21-B20)/H21 -> 0.0003125 | J21: =J20+I21 -> 0.0034375 | K21: =J21*1000 -> 3.4375 | L21: =H21/G21 -> 1 | M21: =1/COUTMAX*(E21/2-C21)*1000 -> 1.9663082 | N21: =I21*G21*(A21-B21) -> 0.085983728 | O21: =G21*(A21-B21) -> 275.14793 | P21: =(A21-B21)*(I_Cout_ss*$Q$2+C21) -> 550.29586 | Q21: =(A21-B21)*(I_Cout_ss*$R$2+C21) -> 103.18047 | X21: C_timer | Y21: 0.2
A22: =VINMAX -> 50 | B22: =VINMAX*((ROW()-10)/104) -> 5.7692308 | C22: =IF(B22>=$H$2,IF($D$2="CC", $G$2, B22/$G$2), 0) -> 0 | D22: =B2 -> 703.33333 | E22: =MIN(D22/(A22-B22),$C$2) -> 15.901449 | F22: =I_Cout_ss+C22 -> 6.1538462 | G22: =IF($F$2="YES", F22, E22) -> 6.1538462 | H22: =G22-C22 -> 6.1538462 | I22: =(COUTMAX/1000000)*(B22-B21)/H22 -> 0.0003125 | J22: =J21+I22 -> 0.00375 | K22: =J22*1000 -> 3.75 | L22: =H22/G22 -> 1 | M22: =1/COUTMAX*(E22/2-C22)*1000 -> 1.9876812 | N22: =I22*G22*(A22-B22) -> 0.085059172 | O22: =G22*(A22-B22) -> 272.18935 | P22: =(A22-B22)*(I_Cout_ss*$Q$2+C22) -> 544.3787 | Q22: =(A22-B22)*(I_Cout_ss*$R$2+C22) -> 102.07101 | X22: RMS | Y22: =SQRT(Y21^2+Y20^2) -> 0.28284271
A23: =VINMAX -> 50 | B23: =VINMAX*((ROW()-10)/104) -> 6.25 | C23: =IF(B23>=$H$2,IF($D$2="CC", $G$2, B23/$G$2), 0) -> 0 | D23: =B2 -> 703.33333 | E23: =MIN(D23/(A23-B23),$C$2) -> 16.07619 | F23: =I_Cout_ss+C23 -> 6.1538462 | G23: =IF($F$2="YES", F23, E23) -> 6.1538462 | H23: =G23-C23 -> 6.1538462 | I23: =(COUTMAX/1000000)*(B23-B22)/H23 -> 0.0003125 | J23: =J22+I23 -> 0.0040625 | K23: =J23*1000 -> 4.0625 | L23: =H23/G23 -> 1 | M23: =1/COUTMAX*(E23/2-C23)*1000 -> 2.0095238 | N23: =I23*G23*(A23-B23) -> 0.084134615 | O23: =G23*(A23-B23) -> 269.23077 | P23: =(A23-B23)*(I_Cout_ss*$Q$2+C23) -> 538.46154 | Q23: =(A23-B23)*(I_Cout_ss*$R$2+C23) -> 100.96154
A24: =VINMAX -> 50 | B24: =VINMAX*((ROW()-10)/104) -> 6.7307692 | C24: =IF(B24>=$H$2,IF($D$2="CC", $G$2, B24/$G$2), 0) -> 0 | D24: =B2 -> 703.33333 | E24: =MIN(D24/(A24-B24),$C$2) -> 16.254815 | F24: =I_Cout_ss+C24 -> 6.1538462 | G24: =IF($F$2="YES", F24, E24) -> 6.1538462 | H24: =G24-C24 -> 6.1538462 | I24: =(COUTMAX/1000000)*(B24-B23)/H24 -> 0.0003125 | J24: =J23+I24 -> 0.004375 | K24: =J24*1000 -> 4.375 | L24: =H24/G24 -> 1 | M24: =1/COUTMAX*(E24/2-C24)*1000 -> 2.0318519 | N24: =I24*G24*(A24-B24) -> 0.083210059 | O24: =G24*(A24-B24) -> 266.27219 | P24: =(A24-B24)*(I_Cout_ss*$Q$2+C24) -> 532.54438 | Q24: =(A24-B24)*(I_Cout_ss*$R$2+C24) -> 99.852071 | X24: Final | Y24: =SQRT(Y18^2+Y22^2) -> 0.50990195
A25: =VINMAX -> 50 | B25: =VINMAX*((ROW()-10)/104) -> 7.2115385 | C25: =IF(B25>=$H$2,IF($D$2="CC", $G$2, B25/$G$2), 0) -> 0 | D25: =B2 -> 703.33333 | E25: =MIN(D25/(A25-B25),$C$2) -> 16.437453 | F25: =I_Cout_ss+C25 -> 6.1538462 | G25: =IF($F$2="YES", F25, E25) -> 6.1538462 | H25: =G25-C25 -> 6.1538462 | I25: =(COUTMAX/1000000)*(B25-B24)/H25 -> 0.0003125 | J25: =J24+I25 -> 0.0046875 | K25: =J25*1000 -> 4.6875 | L25: =H25/G25 -> 1 | M25: =1/COUTMAX*(E25/2-C25)*1000 -> 2.0546816 | N25: =I25*G25*(A25-B25) -> 0.082285503 | O25: =G25*(A25-B25) -> 263.31361 | P25: =(A25-B25)*(I_Cout_ss*$Q$2+C25) -> 526.62722 | Q25: =(A25-B25)*(I_Cout_ss*$R$2+C25) -> 98.742604
A26: =VINMAX -> 50 | B26: =VINMAX*((ROW()-10)/104) -> 7.6923077 | C26: =IF(B26>=$H$2,IF($D$2="CC", $G$2, B26/$G$2), 0) -> 0 | D26: =B2 -> 703.33333 | E26: =MIN(D26/(A26-B26),$C$2) -> 16.624242 | F26: =I_Cout_ss+C26 -> 6.1538462 | G26: =IF($F$2="YES", F26, E26) -> 6.1538462 | H26: =G26-C26 -> 6.1538462 | I26: =(COUTMAX/1000000)*(B26-B25)/H26 -> 0.0003125 | J26: =J25+I26 -> 0.005 | K26: =J26*1000 -> 5 | L26: =H26/G26 -> 1 | M26: =1/COUTMAX*(E26/2-C26)*1000 -> 2.0780303 | N26: =I26*G26*(A26-B26) -> 0.081360947 | O26: =G26*(A26-B26) -> 260.35503 | P26: =(A26-B26)*(I_Cout_ss*$Q$2+C26) -> 520.71006 | Q26: =(A26-B26)*(I_Cout_ss*$R$2+C26) -> 97.633136
A27: =VINMAX -> 50 | B27: =VINMAX*((ROW()-10)/104) -> 8.1730769 | C27: =IF(B27>=$H$2,IF($D$2="CC", $G$2, B27/$G$2), 0) -> 0 | D27: =B2 -> 703.33333 | E27: =MIN(D27/(A27-B27),$C$2) -> 16.815326 | F27: =I_Cout_ss+C27 -> 6.1538462 | G27: =IF($F$2="YES", F27, E27) -> 6.1538462 | H27: =G27-C27 -> 6.1538462 | I27: =(COUTMAX/1000000)*(B27-B26)/H27 -> 0.0003125 | J27: =J26+I27 -> 0.0053125 | K27: =J27*1000 -> 5.3125 | L27: =H27/G27 -> 1 | M27: =1/COUTMAX*(E27/2-C27)*1000 -> 2.1019157 | N27: =I27*G27*(A27-B27) -> 0.080436391 | O27: =G27*(A27-B27) -> 257.39645 | P27: =(A27-B27)*(I_Cout_ss*$Q$2+C27) -> 514.7929 | Q27: =(A27-B27)*(I_Cout_ss*$R$2+C27) -> 96.523669
A28: =VINMAX -> 50 | B28: =VINMAX*((ROW()-10)/104) -> 8.6538462 | C28: =IF(B28>=$H$2,IF($D$2="CC", $G$2, B28/$G$2), 0) -> 0 | D28: =B2 -> 703.33333 | E28: =MIN(D28/(A28-B28),$C$2) -> 17.010853 | F28: =I_Cout_ss+C28 -> 6.1538462 | G28: =IF($F$2="YES", F28, E28) -> 6.1538462 | H28: =G28-C28 -> 6.1538462 | I28: =(COUTMAX/1000000)*(B28-B27)/H28 -> 0.0003125 | J28: =J27+I28 -> 0.005625 | K28: =J28*1000 -> 5.625 | L28: =H28/G28 -> 1 | M28: =1/COUTMAX*(E28/2-C28)*1000 -> 2.1263566 | N28: =I28*G28*(A28-B28) -> 0.079511834 | O28: =G28*(A28-B28) -> 254.43787 | P28: =(A28-B28)*(I_Cout_ss*$Q$2+C28) -> 508.87574 | Q28: =(A28-B28)*(I_Cout_ss*$R$2+C28) -> 95.414201
A29: =VINMAX -> 50 | B29: =VINMAX*((ROW()-10)/104) -> 9.1346154 | C29: =IF(B29>=$H$2,IF($D$2="CC", $G$2, B29/$G$2), 0) -> 0 | D29: =B2 -> 703.33333 | E29: =MIN(D29/(A29-B29),$C$2) -> 17.21098 | F29: =I_Cout_ss+C29 -> 6.1538462 | G29: =IF($F$2="YES", F29, E29) -> 6.1538462 | H29: =G29-C29 -> 6.1538462 | I29: =(COUTMAX/1000000)*(B29-B28)/H29 -> 0.0003125 | J29: =J28+I29 -> 0.0059375 | K29: =J29*1000 -> 5.9375 | L29: =H29/G29 -> 1 | M29: =1/COUTMAX*(E29/2-C29)*1000 -> 2.1513725 | N29: =I29*G29*(A29-B29) -> 0.078587278 | O29: =G29*(A29-B29) -> 251.47929 | P29: =(A29-B29)*(I_Cout_ss*$Q$2+C29) -> 502.95858 | Q29: =(A29-B29)*(I_Cout_ss*$R$2+C29) -> 94.304734
A30: =VINMAX -> 50 | B30: =VINMAX*((ROW()-10)/104) -> 9.6153846 | C30: =IF(B30>=$H$2,IF($D$2="CC", $G$2, B30/$G$2), 0) -> 0 | D30: =B2 -> 703.33333 | E30: =MIN(D30/(A30-B30),$C$2) -> 17.415873 | F30: =I_Cout_ss+C30 -> 6.1538462 | G30: =IF($F$2="YES", F30, E30) -> 6.1538462 | H30: =G30-C30 -> 6.1538462 | I30: =(COUTMAX/1000000)*(B30-B29)/H30 -> 0.0003125 | J30: =J29+I30 -> 0.00625 | K30: =J30*1000 -> 6.25 | L30: =H30/G30 -> 1 | M30: =1/COUTMAX*(E30/2-C30)*1000 -> 2.1769841 | N30: =I30*G30*(A30-B30) -> 0.077662722 | O30: =G30*(A30-B30) -> 248.52071 | P30: =(A30-B30)*(I_Cout_ss*$Q$2+C30) -> 497.04142 | Q30: =(A30-B30)*(I_Cout_ss*$R$2+C30) -> 93.195266
A31: =VINMAX -> 50 | B31: =VINMAX*((ROW()-10)/104) -> 10.096154 | C31: =IF(B31>=$H$2,IF($D$2="CC", $G$2, B31/$G$2), 0) -> 0 | D31: =B2 -> 703.33333 | E31: =MIN(D31/(A31-B31),$C$2) -> 17.625703 | F31: =I_Cout_ss+C31 -> 6.1538462 | G31: =IF($F$2="YES", F31, E31) -> 6.1538462 | H31: =G31-C31 -> 6.1538462 | I31: =(COUTMAX/1000000)*(B31-B30)/H31 -> 0.0003125 | J31: =J30+I31 -> 0.0065625 | K31: =J31*1000 -> 6.5625 | L31: =H31/G31 -> 1 | M31: =1/COUTMAX*(E31/2-C31)*1000 -> 2.2032129 | N31: =I31*G31*(A31-B31) -> 0.076738166 | O31: =G31*(A31-B31) -> 245.56213 | P31: =(A31-B31)*(I_Cout_ss*$Q$2+C31) -> 491.12426 | Q31: =(A31-B31)*(I_Cout_ss*$R$2+C31) -> 92.085799
A32: =VINMAX -> 50 | B32: =VINMAX*((ROW()-10)/104) -> 10.576923 | C32: =IF(B32>=$H$2,IF($D$2="CC", $G$2, B32/$G$2), 0) -> 0 | D32: =B2 -> 703.33333 | E32: =MIN(D32/(A32-B32),$C$2) -> 17.84065 | F32: =I_Cout_ss+C32 -> 6.1538462 | G32: =IF($F$2="YES", F32, E32) -> 6.1538462 | H32: =G32-C32 -> 6.1538462 | I32: =(COUTMAX/1000000)*(B32-B31)/H32 -> 0.0003125 | J32: =J31+I32 -> 0.006875 | K32: =J32*1000 -> 6.875 | L32: =H32/G32 -> 1 | M32: =1/COUTMAX*(E32/2-C32)*1000 -> 2.2300813 | N32: =I32*G32*(A32-B32) -> 0.075813609 | O32: =G32*(A32-B32) -> 242.60355 | P32: =(A32-B32)*(I_Cout_ss*$Q$2+C32) -> 485.2071 | Q32: =(A32-B32)*(I_Cout_ss*$R$2+C32) -> 90.976331
A33: =VINMAX -> 50 | B33: =VINMAX*((ROW()-10)/104) -> 11.057692 | C33: =IF(B33>=$H$2,IF($D$2="CC", $G$2, B33/$G$2), 0) -> 0 | D33: =B2 -> 703.33333 | E33: =MIN(D33/(A33-B33),$C$2) -> 18.060905 | F33: =I_Cout_ss+C33 -> 6.1538462 | G33: =IF($F$2="YES", F33, E33) -> 6.1538462 | H33: =G33-C33 -> 6.1538462 | I33: =(COUTMAX/1000000)*(B33-B32)/H33 -> 0.0003125 | J33: =J32+I33 -> 0.0071875 | K33: =J33*1000 -> 7.1875 | L33: =H33/G33 -> 1 | M33: =1/COUTMAX*(E33/2-C33)*1000 -> 2.2576132 | N33: =I33*G33*(A33-B33) -> 0.074889053 | O33: =G33*(A33-B33) -> 239.64497 | P33: =(A33-B33)*(I_Cout_ss*$Q$2+C33) -> 479.28994 | Q33: =(A33-B33)*(I_Cout_ss*$R$2+C33) -> 89.866864
A34: =VINMAX -> 50 | B34: =VINMAX*((ROW()-10)/104) -> 11.538462 | C34: =IF(B34>=$H$2,IF($D$2="CC", $G$2, B34/$G$2), 0) -> 0 | D34: =B2 -> 703.33333 | E34: =MIN(D34/(A34-B34),$C$2) -> 18.286667 | F34: =I_Cout_ss+C34 -> 6.1538462 | G34: =IF($F$2="YES", F34, E34) -> 6.1538462 | H34: =G34-C34 -> 6.1538462 | I34: =(COUTMAX/1000000)*(B34-B33)/H34 -> 0.0003125 | J34: =J33+I34 -> 0.0075 | K34: =J34*1000 -> 7.5 | L34: =H34/G34 -> 1 | M34: =1/COUTMAX*(E34/2-C34)*1000 -> 2.2858333 | N34: =I34*G34*(A34-B34) -> 0.073964497 | O34: =G34*(A34-B34) -> 236.68639 | P34: =(A34-B34)*(I_Cout_ss*$Q$2+C34) -> 473.37278 | Q34: =(A34-B34)*(I_Cout_ss*$R$2+C34) -> 88.757396
A35: =VINMAX -> 50 | B35: =VINMAX*((ROW()-10)/104) -> 12.019231 | C35: =IF(B35>=$H$2,IF($D$2="CC", $G$2, B35/$G$2), 0) -> 0 | D35: =B2 -> 703.33333 | E35: =MIN(D35/(A35-B35),$C$2) -> 18.518143 | F35: =I_Cout_ss+C35 -> 6.1538462 | G35: =IF($F$2="YES", F35, E35) -> 6.1538462 | H35: =G35-C35 -> 6.1538462 | I35: =(COUTMAX/1000000)*(B35-B34)/H35 -> 0.0003125 | J35: =J34+I35 -> 0.0078125 | K35: =J35*1000 -> 7.8125 | L35: =H35/G35 -> 1 | M35: =1/COUTMAX*(E35/2-C35)*1000 -> 2.3147679 | N35: =I35*G35*(A35-B35) -> 0.073039941 | O35: =G35*(A35-B35) -> 233.72781 | P35: =(A35-B35)*(I_Cout_ss*$Q$2+C35) -> 467.45562 | Q35: =(A35-B35)*(I_Cout_ss*$R$2+C35) -> 87.647929
A36: =VINMAX -> 50 | B36: =VINMAX*((ROW()-10)/104) -> 12.5 | C36: =IF(B36>=$H$2,IF($D$2="CC", $G$2, B36/$G$2), 0) -> 0 | D36: =B2 -> 703.33333 | E36: =MIN(D36/(A36-B36),$C$2) -> 18.755556 | F36: =I_Cout_ss+C36 -> 6.1538462 | G36: =IF($F$2="YES", F36, E36) -> 6.1538462 | H36: =G36-C36 -> 6.1538462 | I36: =(COUTMAX/1000000)*(B36-B35)/H36 -> 0.0003125 | J36: =J35+I36 -> 0.008125 | K36: =J36*1000 -> 8.125 | L36: =H36/G36 -> 1 | M36: =1/COUTMAX*(E36/2-C36)*1000 -> 2.3444444 | N36: =I36*G36*(A36-B36) -> 0.072115385 | O36: =G36*(A36-B36) -> 230.76923 | P36: =(A36-B36)*(I_Cout_ss*$Q$2+C36) -> 461.53846 | Q36: =(A36-B36)*(I_Cout_ss*$R$2+C36) -> 86.538462
A37: =VINMAX -> 50 | B37: =VINMAX*((ROW()-10)/104) -> 12.980769 | C37: =IF(B37>=$H$2,IF($D$2="CC", $G$2, B37/$G$2), 0) -> 0 | D37: =B2 -> 703.33333 | E37: =MIN(D37/(A37-B37),$C$2) -> 18.999134 | F37: =I_Cout_ss+C37 -> 6.1538462 | G37: =IF($F$2="YES", F37, E37) -> 6.1538462 | H37: =G37-C37 -> 6.1538462 | I37: =(COUTMAX/1000000)*(B37-B36)/H37 -> 0.0003125 | J37: =J36+I37 -> 0.0084375 | K37: =J37*1000 -> 8.4375 | L37: =H37/G37 -> 1 | M37: =1/COUTMAX*(E37/2-C37)*1000 -> 2.3748918 | N37: =I37*G37*(A37-B37) -> 0.071190828 | O37: =G37*(A37-B37) -> 227.81065 | P37: =(A37-B37)*(I_Cout_ss*$Q$2+C37) -> 455.6213 | Q37: =(A37-B37)*(I_Cout_ss*$R$2+C37) -> 85.428994
A38: =VINMAX -> 50 | B38: =VINMAX*((ROW()-10)/104) -> 13.461538 | C38: =IF(B38>=$H$2,IF($D$2="CC", $G$2, B38/$G$2), 0) -> 0 | D38: =B2 -> 703.33333 | E38: =MIN(D38/(A38-B38),$C$2) -> 19.249123 | F38: =I_Cout_ss+C38 -> 6.1538462 | G38: =IF($F$2="YES", F38, E38) -> 6.1538462 | H38: =G38-C38 -> 6.1538462 | I38: =(COUTMAX/1000000)*(B38-B37)/H38 -> 0.0003125 | J38: =J37+I38 -> 0.00875 | K38: =J38*1000 -> 8.75 | L38: =H38/G38 -> 1 | M38: =1/COUTMAX*(E38/2-C38)*1000 -> 2.4061404 | N38: =I38*G38*(A38-B38) -> 0.070266272 | O38: =G38*(A38-B38) -> 224.85207 | P38: =(A38-B38)*(I_Cout_ss*$Q$2+C38) -> 449.70414 | Q38: =(A38-B38)*(I_Cout_ss*$R$2+C38) -> 84.319527
A39: =VINMAX -> 50 | B39: =VINMAX*((ROW()-10)/104) -> 13.942308 | C39: =IF(B39>=$H$2,IF($D$2="CC", $G$2, B39/$G$2), 0) -> 0 | D39: =B2 -> 703.33333 | E39: =MIN(D39/(A39-B39),$C$2) -> 19.505778 | F39: =I_Cout_ss+C39 -> 6.1538462 | G39: =IF($F$2="YES", F39, E39) -> 6.1538462 | H39: =G39-C39 -> 6.1538462 | I39: =(COUTMAX/1000000)*(B39-B38)/H39 -> 0.0003125 | J39: =J38+I39 -> 0.0090625 | K39: =J39*1000 -> 9.0625 | L39: =H39/G39 -> 1 | M39: =1/COUTMAX*(E39/2-C39)*1000 -> 2.4382222 | N39: =I39*G39*(A39-B39) -> 0.069341716 | O39: =G39*(A39-B39) -> 221.89349 | P39: =(A39-B39)*(I_Cout_ss*$Q$2+C39) -> 443.78698 | Q39: =(A39-B39)*(I_Cout_ss*$R$2+C39) -> 83.210059
A40: =VINMAX -> 50 | B40: =VINMAX*((ROW()-10)/104) -> 14.423077 | C40: =IF(B40>=$H$2,IF($D$2="CC", $G$2, B40/$G$2), 0) -> 0 | D40: =B2 -> 703.33333 | E40: =MIN(D40/(A40-B40),$C$2) -> 19.769369 | F40: =I_Cout_ss+C40 -> 6.1538462 | G40: =IF($F$2="YES", F40, E40) -> 6.1538462 | H40: =G40-C40 -> 6.1538462 | I40: =(COUTMAX/1000000)*(B40-B39)/H40 -> 0.0003125 | J40: =J39+I40 -> 0.009375 | K40: =J40*1000 -> 9.375 | L40: =H40/G40 -> 1 | M40: =1/COUTMAX*(E40/2-C40)*1000 -> 2.4711712 | N40: =I40*G40*(A40-B40) -> 0.06841716 | O40: =G40*(A40-B40) -> 218.93491 | P40: =(A40-B40)*(I_Cout_ss*$Q$2+C40) -> 437.86982 | Q40: =(A40-B40)*(I_Cout_ss*$R$2+C40) -> 82.100592
A41: =VINMAX -> 50 | B41: =VINMAX*((ROW()-10)/104) -> 14.903846 | C41: =IF(B41>=$H$2,IF($D$2="CC", $G$2, B41/$G$2), 0) -> 0 | D41: =B2 -> 703.33333 | E41: =MIN(D41/(A41-B41),$C$2) -> 20.040183 | F41: =I_Cout_ss+C41 -> 6.1538462 | G41: =IF($F$2="YES", F41, E41) -> 6.1538462 | H41: =G41-C41 -> 6.1538462 | I41: =(COUTMAX/1000000)*(B41-B40)/H41 -> 0.0003125 | J41: =J40+I41 -> 0.0096875 | K41: =J41*1000 -> 9.6875 | L41: =H41/G41 -> 1 | M41: =1/COUTMAX*(E41/2-C41)*1000 -> 2.5050228 | N41: =I41*G41*(A41-B41) -> 0.067492604 | O41: =G41*(A41-B41) -> 215.97633 | P41: =(A41-B41)*(I_Cout_ss*$Q$2+C41) -> 431.95266 | Q41: =(A41-B41)*(I_Cout_ss*$R$2+C41) -> 80.991124
A42: =VINMAX -> 50 | B42: =VINMAX*((ROW()-10)/104) -> 15.384615 | C42: =IF(B42>=$H$2,IF($D$2="CC", $G$2, B42/$G$2), 0) -> 0 | D42: =B2 -> 703.33333 | E42: =MIN(D42/(A42-B42),$C$2) -> 20.318519 | F42: =I_Cout_ss+C42 -> 6.1538462 | G42: =IF($F$2="YES", F42, E42) -> 6.1538462 | H42: =G42-C42 -> 6.1538462 | I42: =(COUTMAX/1000000)*(B42-B41)/H42 -> 0.0003125 | J42: =J41+I42 -> 0.01 | K42: =J42*1000 -> 10 | L42: =H42/G42 -> 1 | M42: =1/COUTMAX*(E42/2-C42)*1000 -> 2.5398148 | N42: =I42*G42*(A42-B42) -> 0.066568047 | O42: =G42*(A42-B42) -> 213.01775 | P42: =(A42-B42)*(I_Cout_ss*$Q$2+C42) -> 426.0355 | Q42: =(A42-B42)*(I_Cout_ss*$R$2+C42) -> 79.881657
A43: =VINMAX -> 50 | B43: =VINMAX*((ROW()-10)/104) -> 15.865385 | C43: =IF(B43>=$H$2,IF($D$2="CC", $G$2, B43/$G$2), 0) -> 0 | D43: =B2 -> 703.33333 | E43: =MIN(D43/(A43-B43),$C$2) -> 20.604695 | F43: =I_Cout_ss+C43 -> 6.1538462 | G43: =IF($F$2="YES", F43, E43) -> 6.1538462 | H43: =G43-C43 -> 6.1538462 | I43: =(COUTMAX/1000000)*(B43-B42)/H43 -> 0.0003125 | J43: =J42+I43 -> 0.0103125 | K43: =J43*1000 -> 10.3125 | L43: =H43/G43 -> 1 | M43: =1/COUTMAX*(E43/2-C43)*1000 -> 2.5755869 | N43: =I43*G43*(A43-B43) -> 0.065643491 | O43: =G43*(A43-B43) -> 210.05917 | P43: =(A43-B43)*(I_Cout_ss*$Q$2+C43) -> 420.11834 | Q43: =(A43-B43)*(I_Cout_ss*$R$2+C43) -> 78.772189
A44: =VINMAX -> 50 | B44: =VINMAX*((ROW()-10)/104) -> 16.346154 | C44: =IF(B44>=$H$2,IF($D$2="CC", $G$2, B44/$G$2), 0) -> 0 | D44: =B2 -> 703.33333 | E44: =MIN(D44/(A44-B44),$C$2) -> 20.899048 | F44: =I_Cout_ss+C44 -> 6.1538462 | G44: =IF($F$2="YES", F44, E44) -> 6.1538462 | H44: =G44-C44 -> 6.1538462 | I44: =(COUTMAX/1000000)*(B44-B43)/H44 -> 0.0003125 | J44: =J43+I44 -> 0.010625 | K44: =J44*1000 -> 10.625 | L44: =H44/G44 -> 1 | M44: =1/COUTMAX*(E44/2-C44)*1000 -> 2.612381 | N44: =I44*G44*(A44-B44) -> 0.064718935 | O44: =G44*(A44-B44) -> 207.10059 | P44: =(A44-B44)*(I_Cout_ss*$Q$2+C44) -> 414.20118 | Q44: =(A44-B44)*(I_Cout_ss*$R$2+C44) -> 77.662722
A45: =VINMAX -> 50 | B45: =VINMAX*((ROW()-10)/104) -> 16.826923 | C45: =IF(B45>=$H$2,IF($D$2="CC", $G$2, B45/$G$2), 0) -> 0 | D45: =B2 -> 703.33333 | E45: =MIN(D45/(A45-B45),$C$2) -> 21.201932 | F45: =I_Cout_ss+C45 -> 6.1538462 | G45: =IF($F$2="YES", F45, E45) -> 6.1538462 | H45: =G45-C45 -> 6.1538462 | I45: =(COUTMAX/1000000)*(B45-B44)/H45 -> 0.0003125 | J45: =J44+I45 -> 0.0109375 | K45: =J45*1000 -> 10.9375 | L45: =H45/G45 -> 1 | M45: =1/COUTMAX*(E45/2-C45)*1000 -> 2.6502415 | N45: =I45*G45*(A45-B45) -> 0.063794379 | O45: =G45*(A45-B45) -> 204.14201 | P45: =(A45-B45)*(I_Cout_ss*$Q$2+C45) -> 408.28402 | Q45: =(A45-B45)*(I_Cout_ss*$R$2+C45) -> 76.553254
A46: =VINMAX -> 50 | B46: =VINMAX*((ROW()-10)/104) -> 17.307692 | C46: =IF(B46>=$H$2,IF($D$2="CC", $G$2, B46/$G$2), 0) -> 0 | D46: =B2 -> 703.33333 | E46: =MIN(D46/(A46-B46),$C$2) -> 21.513725 | F46: =I_Cout_ss+C46 -> 6.1538462 | G46: =IF($F$2="YES", F46, E46) -> 6.1538462 | H46: =G46-C46 -> 6.1538462 | I46: =(COUTMAX/1000000)*(B46-B45)/H46 -> 0.0003125 | J46: =J45+I46 -> 0.01125 | K46: =J46*1000 -> 11.25 | L46: =H46/G46 -> 1 | M46: =1/COUTMAX*(E46/2-C46)*1000 -> 2.6892157 | N46: =I46*G46*(A46-B46) -> 0.062869822 | O46: =G46*(A46-B46) -> 201.18343 | P46: =(A46-B46)*(I_Cout_ss*$Q$2+C46) -> 402.36686 | Q46: =(A46-B46)*(I_Cout_ss*$R$2+C46) -> 75.443787
A47: =VINMAX -> 50 | B47: =VINMAX*((ROW()-10)/104) -> 17.788462 | C47: =IF(B47>=$H$2,IF($D$2="CC", $G$2, B47/$G$2), 0) -> 0 | D47: =B2 -> 703.33333 | E47: =MIN(D47/(A47-B47),$C$2) -> 21.834826 | F47: =I_Cout_ss+C47 -> 6.1538462 | G47: =IF($F$2="YES", F47, E47) -> 6.1538462 | H47: =G47-C47 -> 6.1538462 | I47: =(COUTMAX/1000000)*(B47-B46)/H47 -> 0.0003125 | J47: =J46+I47 -> 0.0115625 | K47: =J47*1000 -> 11.5625 | L47: =H47/G47 -> 1 | M47: =1/COUTMAX*(E47/2-C47)*1000 -> 2.7293532 | N47: =I47*G47*(A47-B47) -> 0.061945266 | O47: =G47*(A47-B47) -> 198.22485 | P47: =(A47-B47)*(I_Cout_ss*$Q$2+C47) -> 396.4497 | Q47: =(A47-B47)*(I_Cout_ss*$R$2+C47) -> 74.33432
A48: =VINMAX -> 50 | B48: =VINMAX*((ROW()-10)/104) -> 18.269231 | C48: =IF(B48>=$H$2,IF($D$2="CC", $G$2, B48/$G$2), 0) -> 0 | D48: =B2 -> 703.33333 | E48: =MIN(D48/(A48-B48),$C$2) -> 22.165657 | F48: =I_Cout_ss+C48 -> 6.1538462 | G48: =IF($F$2="YES", F48, E48) -> 6.1538462 | H48: =G48-C48 -> 6.1538462 | I48: =(COUTMAX/1000000)*(B48-B47)/H48 -> 0.0003125 | J48: =J47+I48 -> 0.011875 | K48: =J48*1000 -> 11.875 | L48: =H48/G48 -> 1 | M48: =1/COUTMAX*(E48/2-C48)*1000 -> 2.7707071 | N48: =I48*G48*(A48-B48) -> 0.06102071 | O48: =G48*(A48-B48) -> 195.26627 | P48: =(A48-B48)*(I_Cout_ss*$Q$2+C48) -> 390.53254 | Q48: =(A48-B48)*(I_Cout_ss*$R$2+C48) -> 73.224852
A49: =VINMAX -> 50 | B49: =VINMAX*((ROW()-10)/104) -> 18.75 | C49: =IF(B49>=$H$2,IF($D$2="CC", $G$2, B49/$G$2), 0) -> 0 | D49: =B2 -> 703.33333 | E49: =MIN(D49/(A49-B49),$C$2) -> 22.506667 | F49: =I_Cout_ss+C49 -> 6.1538462 | G49: =IF($F$2="YES", F49, E49) -> 6.1538462 | H49: =G49-C49 -> 6.1538462 | I49: =(COUTMAX/1000000)*(B49-B48)/H49 -> 0.0003125 | J49: =J48+I49 -> 0.0121875 | K49: =J49*1000 -> 12.1875 | L49: =H49/G49 -> 1 | M49: =1/COUTMAX*(E49/2-C49)*1000 -> 2.8133333 | N49: =I49*G49*(A49-B49) -> 0.060096154 | O49: =G49*(A49-B49) -> 192.30769 | P49: =(A49-B49)*(I_Cout_ss*$Q$2+C49) -> 384.61538 | Q49: =(A49-B49)*(I_Cout_ss*$R$2+C49) -> 72.115385
A50: =VINMAX -> 50 | B50: =VINMAX*((ROW()-10)/104) -> 19.230769 | C50: =IF(B50>=$H$2,IF($D$2="CC", $G$2, B50/$G$2), 0) -> 0 | D50: =B2 -> 703.33333 | E50: =MIN(D50/(A50-B50),$C$2) -> 22.858333 | F50: =I_Cout_ss+C50 -> 6.1538462 | G50: =IF($F$2="YES", F50, E50) -> 6.1538462 | H50: =G50-C50 -> 6.1538462 | I50: =(COUTMAX/1000000)*(B50-B49)/H50 -> 0.0003125 | J50: =J49+I50 -> 0.0125 | K50: =J50*1000 -> 12.5 | L50: =H50/G50 -> 1 | M50: =1/COUTMAX*(E50/2-C50)*1000 -> 2.8572917 | N50: =I50*G50*(A50-B50) -> 0.059171598 | O50: =G50*(A50-B50) -> 189.34911 | P50: =(A50-B50)*(I_Cout_ss*$Q$2+C50) -> 378.69822 | Q50: =(A50-B50)*(I_Cout_ss*$R$2+C50) -> 71.005917
A51: =VINMAX -> 50 | B51: =VINMAX*((ROW()-10)/104) -> 19.711538 | C51: =IF(B51>=$H$2,IF($D$2="CC", $G$2, B51/$G$2), 0) -> 0 | D51: =B2 -> 703.33333 | E51: =MIN(D51/(A51-B51),$C$2) -> 23.221164 | F51: =I_Cout_ss+C51 -> 6.1538462 | G51: =IF($F$2="YES", F51, E51) -> 6.1538462 | H51: =G51-C51 -> 6.1538462 | I51: =(COUTMAX/1000000)*(B51-B50)/H51 -> 0.0003125 | J51: =J50+I51 -> 0.0128125 | K51: =J51*1000 -> 12.8125 | L51: =H51/G51 -> 1 | M51: =1/COUTMAX*(E51/2-C51)*1000 -> 2.9026455 | N51: =I51*G51*(A51-B51) -> 0.058247041 | O51: =G51*(A51-B51) -> 186.39053 | P51: =(A51-B51)*(I_Cout_ss*$Q$2+C51) -> 372.78107 | Q51: =(A51-B51)*(I_Cout_ss*$R$2+C51) -> 69.89645
A52: =VINMAX -> 50 | B52: =VINMAX*((ROW()-10)/104) -> 20.192308 | C52: =IF(B52>=$H$2,IF($D$2="CC", $G$2, B52/$G$2), 0) -> 0 | D52: =B2 -> 703.33333 | E52: =MIN(D52/(A52-B52),$C$2) -> 23.595699 | F52: =I_Cout_ss+C52 -> 6.1538462 | G52: =IF($F$2="YES", F52, E52) -> 6.1538462 | H52: =G52-C52 -> 6.1538462 | I52: =(COUTMAX/1000000)*(B52-B51)/H52 -> 0.0003125 | J52: =J51+I52 -> 0.013125 | K52: =J52*1000 -> 13.125 | L52: =H52/G52 -> 1 | M52: =1/COUTMAX*(E52/2-C52)*1000 -> 2.9494624 | N52: =I52*G52*(A52-B52) -> 0.057322485 | O52: =G52*(A52-B52) -> 183.43195 | P52: =(A52-B52)*(I_Cout_ss*$Q$2+C52) -> 366.86391 | Q52: =(A52-B52)*(I_Cout_ss*$R$2+C52) -> 68.786982
A53: =VINMAX -> 50 | B53: =VINMAX*((ROW()-10)/104) -> 20.673077 | C53: =IF(B53>=$H$2,IF($D$2="CC", $G$2, B53/$G$2), 0) -> 0 | D53: =B2 -> 703.33333 | E53: =MIN(D53/(A53-B53),$C$2) -> 23.982514 | F53: =I_Cout_ss+C53 -> 6.1538462 | G53: =IF($F$2="YES", F53, E53) -> 6.1538462 | H53: =G53-C53 -> 6.1538462 | I53: =(COUTMAX/1000000)*(B53-B52)/H53 -> 0.0003125 | J53: =J52+I53 -> 0.0134375 | K53: =J53*1000 -> 13.4375 | L53: =H53/G53 -> 1 | M53: =1/COUTMAX*(E53/2-C53)*1000 -> 2.9978142 | N53: =I53*G53*(A53-B53) -> 0.056397929 | O53: =G53*(A53-B53) -> 180.47337 | P53: =(A53-B53)*(I_Cout_ss*$Q$2+C53) -> 360.94675 | Q53: =(A53-B53)*(I_Cout_ss*$R$2+C53) -> 67.677515
A54: =VINMAX -> 50 | B54: =VINMAX*((ROW()-10)/104) -> 21.153846 | C54: =IF(B54>=$H$2,IF($D$2="CC", $G$2, B54/$G$2), 0) -> 0 | D54: =B2 -> 703.33333 | E54: =MIN(D54/(A54-B54),$C$2) -> 24.382222 | F54: =I_Cout_ss+C54 -> 6.1538462 | G54: =IF($F$2="YES", F54, E54) -> 6.1538462 | H54: =G54-C54 -> 6.1538462 | I54: =(COUTMAX/1000000)*(B54-B53)/H54 -> 0.0003125 | J54: =J53+I54 -> 0.01375 | K54: =J54*1000 -> 13.75 | L54: =H54/G54 -> 1 | M54: =1/COUTMAX*(E54/2-C54)*1000 -> 3.0477778 | N54: =I54*G54*(A54-B54) -> 0.055473373 | O54: =G54*(A54-B54) -> 177.51479 | P54: =(A54-B54)*(I_Cout_ss*$Q$2+C54) -> 355.02959 | Q54: =(A54-B54)*(I_Cout_ss*$R$2+C54) -> 66.568047
A55: =VINMAX -> 50 | B55: =VINMAX*((ROW()-10)/104) -> 21.634615 | C55: =IF(B55>=$H$2,IF($D$2="CC", $G$2, B55/$G$2), 0) -> 0 | D55: =B2 -> 703.33333 | E55: =MIN(D55/(A55-B55),$C$2) -> 24.79548 | F55: =I_Cout_ss+C55 -> 6.1538462 | G55: =IF($F$2="YES", F55, E55) -> 6.1538462 | H55: =G55-C55 -> 6.1538462 | I55: =(COUTMAX/1000000)*(B55-B54)/H55 -> 0.0003125 | J55: =J54+I55 -> 0.0140625 | K55: =J55*1000 -> 14.0625 | L55: =H55/G55 -> 1 | M55: =1/COUTMAX*(E55/2-C55)*1000 -> 3.099435 | N55: =I55*G55*(A55-B55) -> 0.054548817 | O55: =G55*(A55-B55) -> 174.55621 | P55: =(A55-B55)*(I_Cout_ss*$Q$2+C55) -> 349.11243 | Q55: =(A55-B55)*(I_Cout_ss*$R$2+C55) -> 65.45858
A56: =VINMAX -> 50 | B56: =VINMAX*((ROW()-10)/104) -> 22.115385 | C56: =IF(B56>=$H$2,IF($D$2="CC", $G$2, B56/$G$2), 0) -> 0 | D56: =B2 -> 703.33333 | E56: =MIN(D56/(A56-B56),$C$2) -> 25.222989 | F56: =I_Cout_ss+C56 -> 6.1538462 | G56: =IF($F$2="YES", F56, E56) -> 6.1538462 | H56: =G56-C56 -> 6.1538462 | I56: =(COUTMAX/1000000)*(B56-B55)/H56 -> 0.0003125 | J56: =J55+I56 -> 0.014375 | K56: =J56*1000 -> 14.375 | L56: =H56/G56 -> 1 | M56: =1/COUTMAX*(E56/2-C56)*1000 -> 3.1528736 | N56: =I56*G56*(A56-B56) -> 0.05362426 | O56: =G56*(A56-B56) -> 171.59763 | P56: =(A56-B56)*(I_Cout_ss*$Q$2+C56) -> 343.19527 | Q56: =(A56-B56)*(I_Cout_ss*$R$2+C56) -> 64.349112
A57: =VINMAX -> 50 | B57: =VINMAX*((ROW()-10)/104) -> 22.596154 | C57: =IF(B57>=$H$2,IF($D$2="CC", $G$2, B57/$G$2), 0) -> 0 | D57: =B2 -> 703.33333 | E57: =MIN(D57/(A57-B57),$C$2) -> 25.665497 | F57: =I_Cout_ss+C57 -> 6.1538462 | G57: =IF($F$2="YES", F57, E57) -> 6.1538462 | H57: =G57-C57 -> 6.1538462 | I57: =(COUTMAX/1000000)*(B57-B56)/H57 -> 0.0003125 | J57: =J56+I57 -> 0.0146875 | K57: =J57*1000 -> 14.6875 | L57: =H57/G57 -> 1 | M57: =1/COUTMAX*(E57/2-C57)*1000 -> 3.2081871 | N57: =I57*G57*(A57-B57) -> 0.052699704 | O57: =G57*(A57-B57) -> 168.63905 | P57: =(A57-B57)*(I_Cout_ss*$Q$2+C57) -> 337.27811 | Q57: =(A57-B57)*(I_Cout_ss*$R$2+C57) -> 63.239645
A58: =VINMAX -> 50 | B58: =VINMAX*((ROW()-10)/104) -> 23.076923 | C58: =IF(B58>=$H$2,IF($D$2="CC", $G$2, B58/$G$2), 0) -> 0 | D58: =B2 -> 703.33333 | E58: =MIN(D58/(A58-B58),$C$2) -> 26.12381 | F58: =I_Cout_ss+C58 -> 6.1538462 | G58: =IF($F$2="YES", F58, E58) -> 6.1538462 | H58: =G58-C58 -> 6.1538462 | I58: =(COUTMAX/1000000)*(B58-B57)/H58 -> 0.0003125 | J58: =J57+I58 -> 0.015 | K58: =J58*1000 -> 15 | L58: =H58/G58 -> 1 | M58: =1/COUTMAX*(E58/2-C58)*1000 -> 3.2654762 | N58: =I58*G58*(A58-B58) -> 0.051775148 | O58: =G58*(A58-B58) -> 165.68047 | P58: =(A58-B58)*(I_Cout_ss*$Q$2+C58) -> 331.36095 | Q58: =(A58-B58)*(I_Cout_ss*$R$2+C58) -> 62.130178
A59: =VINMAX -> 50 | B59: =VINMAX*((ROW()-10)/104) -> 23.557692 | C59: =IF(B59>=$H$2,IF($D$2="CC", $G$2, B59/$G$2), 0) -> 0 | D59: =B2 -> 703.33333 | E59: =MIN(D59/(A59-B59),$C$2) -> 26.598788 | F59: =I_Cout_ss+C59 -> 6.1538462 | G59: =IF($F$2="YES", F59, E59) -> 6.1538462 | H59: =G59-C59 -> 6.1538462 | I59: =(COUTMAX/1000000)*(B59-B58)/H59 -> 0.0003125 | J59: =J58+I59 -> 0.0153125 | K59: =J59*1000 -> 15.3125 | L59: =H59/G59 -> 1 | M59: =1/COUTMAX*(E59/2-C59)*1000 -> 3.3248485 | N59: =I59*G59*(A59-B59) -> 0.050850592 | O59: =G59*(A59-B59) -> 162.72189 | P59: =(A59-B59)*(I_Cout_ss*$Q$2+C59) -> 325.44379 | Q59: =(A59-B59)*(I_Cout_ss*$R$2+C59) -> 61.02071
A60: =VINMAX -> 50 | B60: =VINMAX*((ROW()-10)/104) -> 24.038462 | C60: =IF(B60>=$H$2,IF($D$2="CC", $G$2, B60/$G$2), 0) -> 0 | D60: =B2 -> 703.33333 | E60: =MIN(D60/(A60-B60),$C$2) -> 27.091358 | F60: =I_Cout_ss+C60 -> 6.1538462 | G60: =IF($F$2="YES", F60, E60) -> 6.1538462 | H60: =G60-C60 -> 6.1538462 | I60: =(COUTMAX/1000000)*(B60-B59)/H60 -> 0.0003125 | J60: =J59+I60 -> 0.015625 | K60: =J60*1000 -> 15.625 | L60: =H60/G60 -> 1 | M60: =1/COUTMAX*(E60/2-C60)*1000 -> 3.3864198 | N60: =I60*G60*(A60-B60) -> 0.049926036 | O60: =G60*(A60-B60) -> 159.76331 | P60: =(A60-B60)*(I_Cout_ss*$Q$2+C60) -> 319.52663 | Q60: =(A60-B60)*(I_Cout_ss*$R$2+C60) -> 59.911243
A61: =VINMAX -> 50 | B61: =VINMAX*((ROW()-10)/104) -> 24.519231 | C61: =IF(B61>=$H$2,IF($D$2="CC", $G$2, B61/$G$2), 0) -> 0 | D61: =B2 -> 703.33333 | E61: =MIN(D61/(A61-B61),$C$2) -> 27.602516 | F61: =I_Cout_ss+C61 -> 6.1538462 | G61: =IF($F$2="YES", F61, E61) -> 6.1538462 | H61: =G61-C61 -> 6.1538462 | I61: =(COUTMAX/1000000)*(B61-B60)/H61 -> 0.0003125 | J61: =J60+I61 -> 0.0159375 | K61: =J61*1000 -> 15.9375 | L61: =H61/G61 -> 1 | M61: =1/COUTMAX*(E61/2-C61)*1000 -> 3.4503145 | N61: =I61*G61*(A61-B61) -> 0.049001479 | O61: =G61*(A61-B61) -> 156.80473 | P61: =(A61-B61)*(I_Cout_ss*$Q$2+C61) -> 313.60947 | Q61: =(A61-B61)*(I_Cout_ss*$R$2+C61) -> 58.801775
A62: =VINMAX -> 50 | B62: =VINMAX*((ROW()-10)/104) -> 25 | C62: =IF(B62>=$H$2,IF($D$2="CC", $G$2, B62/$G$2), 0) -> 0 | D62: =B2 -> 703.33333 | E62: =MIN(D62/(A62-B62),$C$2) -> 28.133333 | F62: =I_Cout_ss+C62 -> 6.1538462 | G62: =IF($F$2="YES", F62, E62) -> 6.1538462 | H62: =G62-C62 -> 6.1538462 | I62: =(COUTMAX/1000000)*(B62-B61)/H62 -> 0.0003125 | J62: =J61+I62 -> 0.01625 | K62: =J62*1000 -> 16.25 | L62: =H62/G62 -> 1 | M62: =1/COUTMAX*(E62/2-C62)*1000 -> 3.5166667 | N62: =I62*G62*(A62-B62) -> 0.048076923 | O62: =G62*(A62-B62) -> 153.84615 | P62: =(A62-B62)*(I_Cout_ss*$Q$2+C62) -> 307.69231 | Q62: =(A62-B62)*(I_Cout_ss*$R$2+C62) -> 57.692308
A63: =VINMAX -> 50 | B63: =VINMAX*((ROW()-10)/104) -> 25.480769 | C63: =IF(B63>=$H$2,IF($D$2="CC", $G$2, B63/$G$2), 0) -> 0 | D63: =B2 -> 703.33333 | E63: =MIN(D63/(A63-B63),$C$2) -> 28.684967 | F63: =I_Cout_ss+C63 -> 6.1538462 | G63: =IF($F$2="YES", F63, E63) -> 6.1538462 | H63: =G63-C63 -> 6.1538462 | I63: =(COUTMAX/1000000)*(B63-B62)/H63 -> 0.0003125 | J63: =J62+I63 -> 0.0165625 | K63: =J63*1000 -> 16.5625 | L63: =H63/G63 -> 1 | M63: =1/COUTMAX*(E63/2-C63)*1000 -> 3.5856209 | N63: =I63*G63*(A63-B63) -> 0.047152367 | O63: =G63*(A63-B63) -> 150.88757 | P63: =(A63-B63)*(I_Cout_ss*$Q$2+C63) -> 301.77515 | Q63: =(A63-B63)*(I_Cout_ss*$R$2+C63) -> 56.58284
A64: =VINMAX -> 50 | B64: =VINMAX*((ROW()-10)/104) -> 25.961538 | C64: =IF(B64>=$H$2,IF($D$2="CC", $G$2, B64/$G$2), 0) -> 0 | D64: =B2 -> 703.33333 | E64: =MIN(D64/(A64-B64),$C$2) -> 29.258667 | F64: =I_Cout_ss+C64 -> 6.1538462 | G64: =IF($F$2="YES", F64, E64) -> 6.1538462 | H64: =G64-C64 -> 6.1538462 | I64: =(COUTMAX/1000000)*(B64-B63)/H64 -> 0.0003125 | J64: =J63+I64 -> 0.016875 | K64: =J64*1000 -> 16.875 | L64: =H64/G64 -> 1 | M64: =1/COUTMAX*(E64/2-C64)*1000 -> 3.6573333 | N64: =I64*G64*(A64-B64) -> 0.046227811 | O64: =G64*(A64-B64) -> 147.92899 | P64: =(A64-B64)*(I_Cout_ss*$Q$2+C64) -> 295.85799 | Q64: =(A64-B64)*(I_Cout_ss*$R$2+C64) -> 55.473373
A65: =VINMAX -> 50 | B65: =VINMAX*((ROW()-10)/104) -> 26.442308 | C65: =IF(B65>=$H$2,IF($D$2="CC", $G$2, B65/$G$2), 0) -> 0 | D65: =B2 -> 703.33333 | E65: =MIN(D65/(A65-B65),$C$2) -> 29.855782 | F65: =I_Cout_ss+C65 -> 6.1538462 | G65: =IF($F$2="YES", F65, E65) -> 6.1538462 | H65: =G65-C65 -> 6.1538462 | I65: =(COUTMAX/1000000)*(B65-B64)/H65 -> 0.0003125 | J65: =J64+I65 -> 0.0171875 | K65: =J65*1000 -> 17.1875 | L65: =H65/G65 -> 1 | M65: =1/COUTMAX*(E65/2-C65)*1000 -> 3.7319728 | N65: =I65*G65*(A65-B65) -> 0.045303254 | O65: =G65*(A65-B65) -> 144.97041 | P65: =(A65-B65)*(I_Cout_ss*$Q$2+C65) -> 289.94083 | Q65: =(A65-B65)*(I_Cout_ss*$R$2+C65) -> 54.363905
A66: =VINMAX -> 50 | B66: =VINMAX*((ROW()-10)/104) -> 26.923077 | C66: =IF(B66>=$H$2,IF($D$2="CC", $G$2, B66/$G$2), 0) -> 0 | D66: =B2 -> 703.33333 | E66: =MIN(D66/(A66-B66),$C$2) -> 30.477778 | F66: =I_Cout_ss+C66 -> 6.1538462 | G66: =IF($F$2="YES", F66, E66) -> 6.1538462 | H66: =G66-C66 -> 6.1538462 | I66: =(COUTMAX/1000000)*(B66-B65)/H66 -> 0.0003125 | J66: =J65+I66 -> 0.0175 | K66: =J66*1000 -> 17.5 | L66: =H66/G66 -> 1 | M66: =1/COUTMAX*(E66/2-C66)*1000 -> 3.8097222 | N66: =I66*G66*(A66-B66) -> 0.044378698 | O66: =G66*(A66-B66) -> 142.01183 | P66: =(A66-B66)*(I_Cout_ss*$Q$2+C66) -> 284.02367 | Q66: =(A66-B66)*(I_Cout_ss*$R$2+C66) -> 53.254438
A67: =VINMAX -> 50 | B67: =VINMAX*((ROW()-10)/104) -> 27.403846 | C67: =IF(B67>=$H$2,IF($D$2="CC", $G$2, B67/$G$2), 0) -> 0 | D67: =B2 -> 703.33333 | E67: =MIN(D67/(A67-B67),$C$2) -> 31.126241 | F67: =I_Cout_ss+C67 -> 6.1538462 | G67: =IF($F$2="YES", F67, E67) -> 6.1538462 | H67: =G67-C67 -> 6.1538462 | I67: =(COUTMAX/1000000)*(B67-B66)/H67 -> 0.0003125 | J67: =J66+I67 -> 0.0178125 | K67: =J67*1000 -> 17.8125 | L67: =H67/G67 -> 1 | M67: =1/COUTMAX*(E67/2-C67)*1000 -> 3.8907801 | N67: =I67*G67*(A67-B67) -> 0.043454142 | O67: =G67*(A67-B67) -> 139.05325 | P67: =(A67-B67)*(I_Cout_ss*$Q$2+C67) -> 278.10651 | Q67: =(A67-B67)*(I_Cout_ss*$R$2+C67) -> 52.14497
A68: =VINMAX -> 50 | B68: =VINMAX*((ROW()-10)/104) -> 27.884615 | C68: =IF(B68>=$H$2,IF($D$2="CC", $G$2, B68/$G$2), 0) -> 0 | D68: =B2 -> 703.33333 | E68: =MIN(D68/(A68-B68),$C$2) -> 31.802899 | F68: =I_Cout_ss+C68 -> 6.1538462 | G68: =IF($F$2="YES", F68, E68) -> 6.1538462 | H68: =G68-C68 -> 6.1538462 | I68: =(COUTMAX/1000000)*(B68-B67)/H68 -> 0.0003125 | J68: =J67+I68 -> 0.018125 | K68: =J68*1000 -> 18.125 | L68: =H68/G68 -> 1 | M68: =1/COUTMAX*(E68/2-C68)*1000 -> 3.9753623 | N68: =I68*G68*(A68-B68) -> 0.042529586 | O68: =G68*(A68-B68) -> 136.09467 | P68: =(A68-B68)*(I_Cout_ss*$Q$2+C68) -> 272.18935 | Q68: =(A68-B68)*(I_Cout_ss*$R$2+C68) -> 51.035503
A69: =VINMAX -> 50 | B69: =VINMAX*((ROW()-10)/104) -> 28.365385 | C69: =IF(B69>=$H$2,IF($D$2="CC", $G$2, B69/$G$2), 0) -> 0 | D69: =B2 -> 703.33333 | E69: =MIN(D69/(A69-B69),$C$2) -> 32.50963 | F69: =I_Cout_ss+C69 -> 6.1538462 | G69: =IF($F$2="YES", F69, E69) -> 6.1538462 | H69: =G69-C69 -> 6.1538462 | I69: =(COUTMAX/1000000)*(B69-B68)/H69 -> 0.0003125 | J69: =J68+I69 -> 0.0184375 | K69: =J69*1000 -> 18.4375 | L69: =H69/G69 -> 1 | M69: =1/COUTMAX*(E69/2-C69)*1000 -> 4.0637037 | N69: =I69*G69*(A69-B69) -> 0.04160503 | O69: =G69*(A69-B69) -> 133.13609 | P69: =(A69-B69)*(I_Cout_ss*$Q$2+C69) -> 266.27219 | Q69: =(A69-B69)*(I_Cout_ss*$R$2+C69) -> 49.926036
A70: =VINMAX -> 50 | B70: =VINMAX*((ROW()-10)/104) -> 28.846154 | C70: =IF(B70>=$H$2,IF($D$2="CC", $G$2, B70/$G$2), 0) -> 0 | D70: =B2 -> 703.33333 | E70: =MIN(D70/(A70-B70),$C$2) -> 33.248485 | F70: =I_Cout_ss+C70 -> 6.1538462 | G70: =IF($F$2="YES", F70, E70) -> 6.1538462 | H70: =G70-C70 -> 6.1538462 | I70: =(COUTMAX/1000000)*(B70-B69)/H70 -> 0.0003125 | J70: =J69+I70 -> 0.01875 | K70: =J70*1000 -> 18.75 | L70: =H70/G70 -> 1 | M70: =1/COUTMAX*(E70/2-C70)*1000 -> 4.1560606 | N70: =I70*G70*(A70-B70) -> 0.040680473 | O70: =G70*(A70-B70) -> 130.17751 | P70: =(A70-B70)*(I_Cout_ss*$Q$2+C70) -> 260.35503 | Q70: =(A70-B70)*(I_Cout_ss*$R$2+C70) -> 48.816568
A71: =VINMAX -> 50 | B71: =VINMAX*((ROW()-10)/104) -> 29.326923 | C71: =IF(B71>=$H$2,IF($D$2="CC", $G$2, B71/$G$2), 0) -> 0 | D71: =B2 -> 703.33333 | E71: =MIN(D71/(A71-B71),$C$2) -> 34.021705 | F71: =I_Cout_ss+C71 -> 6.1538462 | G71: =IF($F$2="YES", F71, E71) -> 6.1538462 | H71: =G71-C71 -> 6.1538462 | I71: =(COUTMAX/1000000)*(B71-B70)/H71 -> 0.0003125 | J71: =J70+I71 -> 0.0190625 | K71: =J71*1000 -> 19.0625 | L71: =H71/G71 -> 1 | M71: =1/COUTMAX*(E71/2-C71)*1000 -> 4.2527132 | N71: =I71*G71*(A71-B71) -> 0.039755917 | O71: =G71*(A71-B71) -> 127.21893 | P71: =(A71-B71)*(I_Cout_ss*$Q$2+C71) -> 254.43787 | Q71: =(A71-B71)*(I_Cout_ss*$R$2+C71) -> 47.707101
A72: =VINMAX -> 50 | B72: =VINMAX*((ROW()-10)/104) -> 29.807692 | C72: =IF(B72>=$H$2,IF($D$2="CC", $G$2, B72/$G$2), 0) -> 0 | D72: =B2 -> 703.33333 | E72: =MIN(D72/(A72-B72),$C$2) -> 34.831746 | F72: =I_Cout_ss+C72 -> 6.1538462 | G72: =IF($F$2="YES", F72, E72) -> 6.1538462 | H72: =G72-C72 -> 6.1538462 | I72: =(COUTMAX/1000000)*(B72-B71)/H72 -> 0.0003125 | J72: =J71+I72 -> 0.019375 | K72: =J72*1000 -> 19.375 | L72: =H72/G72 -> 1 | M72: =1/COUTMAX*(E72/2-C72)*1000 -> 4.3539683 | N72: =I72*G72*(A72-B72) -> 0.038831361 | O72: =G72*(A72-B72) -> 124.26036 | P72: =(A72-B72)*(I_Cout_ss*$Q$2+C72) -> 248.52071 | Q72: =(A72-B72)*(I_Cout_ss*$R$2+C72) -> 46.597633
A73: =VINMAX -> 50 | B73: =VINMAX*((ROW()-10)/104) -> 30.288462 | C73: =IF(B73>=$H$2,IF($D$2="CC", $G$2, B73/$G$2), 0) -> 0 | D73: =B2 -> 703.33333 | E73: =MIN(D73/(A73-B73),$C$2) -> 35.681301 | F73: =I_Cout_ss+C73 -> 6.1538462 | G73: =IF($F$2="YES", F73, E73) -> 6.1538462 | H73: =G73-C73 -> 6.1538462 | I73: =(COUTMAX/1000000)*(B73-B72)/H73 -> 0.0003125 | J73: =J72+I73 -> 0.0196875 | K73: =J73*1000 -> 19.6875 | L73: =H73/G73 -> 1 | M73: =1/COUTMAX*(E73/2-C73)*1000 -> 4.4601626 | N73: =I73*G73*(A73-B73) -> 0.037906805 | O73: =G73*(A73-B73) -> 121.30178 | P73: =(A73-B73)*(I_Cout_ss*$Q$2+C73) -> 242.60355 | Q73: =(A73-B73)*(I_Cout_ss*$R$2+C73) -> 45.488166
A74: =VINMAX -> 50 | B74: =VINMAX*((ROW()-10)/104) -> 30.769231 | C74: =IF(B74>=$H$2,IF($D$2="CC", $G$2, B74/$G$2), 0) -> 0 | D74: =B2 -> 703.33333 | E74: =MIN(D74/(A74-B74),$C$2) -> 36.573333 | F74: =I_Cout_ss+C74 -> 6.1538462 | G74: =IF($F$2="YES", F74, E74) -> 6.1538462 | H74: =G74-C74 -> 6.1538462 | I74: =(COUTMAX/1000000)*(B74-B73)/H74 -> 0.0003125 | J74: =J73+I74 -> 0.02 | K74: =J74*1000 -> 20 | L74: =H74/G74 -> 1 | M74: =1/COUTMAX*(E74/2-C74)*1000 -> 4.5716667 | N74: =I74*G74*(A74-B74) -> 0.036982249 | O74: =G74*(A74-B74) -> 118.3432 | P74: =(A74-B74)*(I_Cout_ss*$Q$2+C74) -> 236.68639 | Q74: =(A74-B74)*(I_Cout_ss*$R$2+C74) -> 44.378698
A75: =VINMAX -> 50 | B75: =VINMAX*((ROW()-10)/104) -> 31.25 | C75: =IF(B75>=$H$2,IF($D$2="CC", $G$2, B75/$G$2), 0) -> 0 | D75: =B2 -> 703.33333 | E75: =MIN(D75/(A75-B75),$C$2) -> 37.511111 | F75: =I_Cout_ss+C75 -> 6.1538462 | G75: =IF($F$2="YES", F75, E75) -> 6.1538462 | H75: =G75-C75 -> 6.1538462 | I75: =(COUTMAX/1000000)*(B75-B74)/H75 -> 0.0003125 | J75: =J74+I75 -> 0.0203125 | K75: =J75*1000 -> 20.3125 | L75: =H75/G75 -> 1 | M75: =1/COUTMAX*(E75/2-C75)*1000 -> 4.6888889 | N75: =I75*G75*(A75-B75) -> 0.036057692 | O75: =G75*(A75-B75) -> 115.38462 | P75: =(A75-B75)*(I_Cout_ss*$Q$2+C75) -> 230.76923 | Q75: =(A75-B75)*(I_Cout_ss*$R$2+C75) -> 43.269231
A76: =VINMAX -> 50 | B76: =VINMAX*((ROW()-10)/104) -> 31.730769 | C76: =IF(B76>=$H$2,IF($D$2="CC", $G$2, B76/$G$2), 0) -> 0 | D76: =B2 -> 703.33333 | E76: =MIN(D76/(A76-B76),$C$2) -> 38.498246 | F76: =I_Cout_ss+C76 -> 6.1538462 | G76: =IF($F$2="YES", F76, E76) -> 6.1538462 | H76: =G76-C76 -> 6.1538462 | I76: =(COUTMAX/1000000)*(B76-B75)/H76 -> 0.0003125 | J76: =J75+I76 -> 0.020625 | K76: =J76*1000 -> 20.625 | L76: =H76/G76 -> 1 | M76: =1/COUTMAX*(E76/2-C76)*1000 -> 4.8122807 | N76: =I76*G76*(A76-B76) -> 0.035133136 | O76: =G76*(A76-B76) -> 112.42604 | P76: =(A76-B76)*(I_Cout_ss*$Q$2+C76) -> 224.85207 | Q76: =(A76-B76)*(I_Cout_ss*$R$2+C76) -> 42.159763
A77: =VINMAX -> 50 | B77: =VINMAX*((ROW()-10)/104) -> 32.211538 | C77: =IF(B77>=$H$2,IF($D$2="CC", $G$2, B77/$G$2), 0) -> 0 | D77: =B2 -> 703.33333 | E77: =MIN(D77/(A77-B77),$C$2) -> 39.538739 | F77: =I_Cout_ss+C77 -> 6.1538462 | G77: =IF($F$2="YES", F77, E77) -> 6.1538462 | H77: =G77-C77 -> 6.1538462 | I77: =(COUTMAX/1000000)*(B77-B76)/H77 -> 0.0003125 | J77: =J76+I77 -> 0.0209375 | K77: =J77*1000 -> 20.9375 | L77: =H77/G77 -> 1 | M77: =1/COUTMAX*(E77/2-C77)*1000 -> 4.9423423 | N77: =I77*G77*(A77-B77) -> 0.03420858 | O77: =G77*(A77-B77) -> 109.46746 | P77: =(A77-B77)*(I_Cout_ss*$Q$2+C77) -> 218.93491 | Q77: =(A77-B77)*(I_Cout_ss*$R$2+C77) -> 41.050296
A78: =VINMAX -> 50 | B78: =VINMAX*((ROW()-10)/104) -> 32.692308 | C78: =IF(B78>=$H$2,IF($D$2="CC", $G$2, B78/$G$2), 0) -> 0 | D78: =B2 -> 703.33333 | E78: =MIN(D78/(A78-B78),$C$2) -> 40.637037 | F78: =I_Cout_ss+C78 -> 6.1538462 | G78: =IF($F$2="YES", F78, E78) -> 6.1538462 | H78: =G78-C78 -> 6.1538462 | I78: =(COUTMAX/1000000)*(B78-B77)/H78 -> 0.0003125 | J78: =J77+I78 -> 0.02125 | K78: =J78*1000 -> 21.25 | L78: =H78/G78 -> 1 | M78: =1/COUTMAX*(E78/2-C78)*1000 -> 5.0796296 | N78: =I78*G78*(A78-B78) -> 0.033284024 | O78: =G78*(A78-B78) -> 106.50888 | P78: =(A78-B78)*(I_Cout_ss*$Q$2+C78) -> 213.01775 | Q78: =(A78-B78)*(I_Cout_ss*$R$2+C78) -> 39.940828
A79: =VINMAX -> 50 | B79: =VINMAX*((ROW()-10)/104) -> 33.173077 | C79: =IF(B79>=$H$2,IF($D$2="CC", $G$2, B79/$G$2), 0) -> 0 | D79: =B2 -> 703.33333 | E79: =MIN(D79/(A79-B79),$C$2) -> 41.798095 | F79: =I_Cout_ss+C79 -> 6.1538462 | G79: =IF($F$2="YES", F79, E79) -> 6.1538462 | H79: =G79-C79 -> 6.1538462 | I79: =(COUTMAX/1000000)*(B79-B78)/H79 -> 0.0003125 | J79: =J78+I79 -> 0.0215625 | K79: =J79*1000 -> 21.5625 | L79: =H79/G79 -> 1 | M79: =1/COUTMAX*(E79/2-C79)*1000 -> 5.2247619 | N79: =I79*G79*(A79-B79) -> 0.032359467 | O79: =G79*(A79-B79) -> 103.5503 | P79: =(A79-B79)*(I_Cout_ss*$Q$2+C79) -> 207.10059 | Q79: =(A79-B79)*(I_Cout_ss*$R$2+C79) -> 38.831361
A80: =VINMAX -> 50 | B80: =VINMAX*((ROW()-10)/104) -> 33.653846 | C80: =IF(B80>=$H$2,IF($D$2="CC", $G$2, B80/$G$2), 0) -> 0 | D80: =B2 -> 703.33333 | E80: =MIN(D80/(A80-B80),$C$2) -> 43.027451 | F80: =I_Cout_ss+C80 -> 6.1538462 | G80: =IF($F$2="YES", F80, E80) -> 6.1538462 | H80: =G80-C80 -> 6.1538462 | I80: =(COUTMAX/1000000)*(B80-B79)/H80 -> 0.0003125 | J80: =J79+I80 -> 0.021875 | K80: =J80*1000 -> 21.875 | L80: =H80/G80 -> 1 | M80: =1/COUTMAX*(E80/2-C80)*1000 -> 5.3784314 | N80: =I80*G80*(A80-B80) -> 0.031434911 | O80: =G80*(A80-B80) -> 100.59172 | P80: =(A80-B80)*(I_Cout_ss*$Q$2+C80) -> 201.18343 | Q80: =(A80-B80)*(I_Cout_ss*$R$2+C80) -> 37.721893
A81: =VINMAX -> 50 | B81: =VINMAX*((ROW()-10)/104) -> 34.134615 | C81: =IF(B81>=$H$2,IF($D$2="CC", $G$2, B81/$G$2), 0) -> 0 | D81: =B2 -> 703.33333 | E81: =MIN(D81/(A81-B81),$C$2) -> 44.331313 | F81: =I_Cout_ss+C81 -> 6.1538462 | G81: =IF($F$2="YES", F81, E81) -> 6.1538462 | H81: =G81-C81 -> 6.1538462 | I81: =(COUTMAX/1000000)*(B81-B80)/H81 -> 0.0003125 | J81: =J80+I81 -> 0.0221875 | K81: =J81*1000 -> 22.1875 | L81: =H81/G81 -> 1 | M81: =1/COUTMAX*(E81/2-C81)*1000 -> 5.5414141 | N81: =I81*G81*(A81-B81) -> 0.030510355 | O81: =G81*(A81-B81) -> 97.633136 | P81: =(A81-B81)*(I_Cout_ss*$Q$2+C81) -> 195.26627 | Q81: =(A81-B81)*(I_Cout_ss*$R$2+C81) -> 36.612426
A82: =VINMAX -> 50 | B82: =VINMAX*((ROW()-10)/104) -> 34.615385 | C82: =IF(B82>=$H$2,IF($D$2="CC", $G$2, B82/$G$2), 0) -> 0 | D82: =B2 -> 703.33333 | E82: =MIN(D82/(A82-B82),$C$2) -> 45.716667 | F82: =I_Cout_ss+C82 -> 6.1538462 | G82: =IF($F$2="YES", F82, E82) -> 6.1538462 | H82: =G82-C82 -> 6.1538462 | I82: =(COUTMAX/1000000)*(B82-B81)/H82 -> 0.0003125 | J82: =J81+I82 -> 0.0225 | K82: =J82*1000 -> 22.5 | L82: =H82/G82 -> 1 | M82: =1/COUTMAX*(E82/2-C82)*1000 -> 5.7145833 | N82: =I82*G82*(A82-B82) -> 0.029585799 | O82: =G82*(A82-B82) -> 94.674556 | P82: =(A82-B82)*(I_Cout_ss*$Q$2+C82) -> 189.34911 | Q82: =(A82-B82)*(I_Cout_ss*$R$2+C82) -> 35.502959
A83: =VINMAX -> 50 | B83: =VINMAX*((ROW()-10)/104) -> 35.096154 | C83: =IF(B83>=$H$2,IF($D$2="CC", $G$2, B83/$G$2), 0) -> 0 | D83: =B2 -> 703.33333 | E83: =MIN(D83/(A83-B83),$C$2) -> 47.191398 | F83: =I_Cout_ss+C83 -> 6.1538462 | G83: =IF($F$2="YES", F83, E83) -> 6.1538462 | H83: =G83-C83 -> 6.1538462 | I83: =(COUTMAX/1000000)*(B83-B82)/H83 -> 0.0003125 | J83: =J82+I83 -> 0.0228125 | K83: =J83*1000 -> 22.8125 | L83: =H83/G83 -> 1 | M83: =1/COUTMAX*(E83/2-C83)*1000 -> 5.8989247 | N83: =I83*G83*(A83-B83) -> 0.028661243 | O83: =G83*(A83-B83) -> 91.715976 | P83: =(A83-B83)*(I_Cout_ss*$Q$2+C83) -> 183.43195 | Q83: =(A83-B83)*(I_Cout_ss*$R$2+C83) -> 34.393491
A84: =VINMAX -> 50 | B84: =VINMAX*((ROW()-10)/104) -> 35.576923 | C84: =IF(B84>=$H$2,IF($D$2="CC", $G$2, B84/$G$2), 0) -> 0 | D84: =B2 -> 703.33333 | E84: =MIN(D84/(A84-B84),$C$2) -> 48.764444 | F84: =I_Cout_ss+C84 -> 6.1538462 | G84: =IF($F$2="YES", F84, E84) -> 6.1538462 | H84: =G84-C84 -> 6.1538462 | I84: =(COUTMAX/1000000)*(B84-B83)/H84 -> 0.0003125 | J84: =J83+I84 -> 0.023125 | K84: =J84*1000 -> 23.125 | L84: =H84/G84 -> 1 | M84: =1/COUTMAX*(E84/2-C84)*1000 -> 6.0955556 | N84: =I84*G84*(A84-B84) -> 0.027736686 | O84: =G84*(A84-B84) -> 88.757396 | P84: =(A84-B84)*(I_Cout_ss*$Q$2+C84) -> 177.51479 | Q84: =(A84-B84)*(I_Cout_ss*$R$2+C84) -> 33.284024
A85: =VINMAX -> 50 | B85: =VINMAX*((ROW()-10)/104) -> 36.057692 | C85: =IF(B85>=$H$2,IF($D$2="CC", $G$2, B85/$G$2), 0) -> 0 | D85: =B2 -> 703.33333 | E85: =MIN(D85/(A85-B85),$C$2) -> 50.445977 | F85: =I_Cout_ss+C85 -> 6.1538462 | G85: =IF($F$2="YES", F85, E85) -> 6.1538462 | H85: =G85-C85 -> 6.1538462 | I85: =(COUTMAX/1000000)*(B85-B84)/H85 -> 0.0003125 | J85: =J84+I85 -> 0.0234375 | K85: =J85*1000 -> 23.4375 | L85: =H85/G85 -> 1 | M85: =1/COUTMAX*(E85/2-C85)*1000 -> 6.3057471 | N85: =I85*G85*(A85-B85) -> 0.02681213 | O85: =G85*(A85-B85) -> 85.798817 | P85: =(A85-B85)*(I_Cout_ss*$Q$2+C85) -> 171.59763 | Q85: =(A85-B85)*(I_Cout_ss*$R$2+C85) -> 32.174556
A86: =VINMAX -> 50 | B86: =VINMAX*((ROW()-10)/104) -> 36.538462 | C86: =IF(B86>=$H$2,IF($D$2="CC", $G$2, B86/$G$2), 0) -> 0 | D86: =B2 -> 703.33333 | E86: =MIN(D86/(A86-B86),$C$2) -> 52.247619 | F86: =I_Cout_ss+C86 -> 6.1538462 | G86: =IF($F$2="YES", F86, E86) -> 6.1538462 | H86: =G86-C86 -> 6.1538462 | I86: =(COUTMAX/1000000)*(B86-B85)/H86 -> 0.0003125 | J86: =J85+I86 -> 0.02375 | K86: =J86*1000 -> 23.75 | L86: =H86/G86 -> 1 | M86: =1/COUTMAX*(E86/2-C86)*1000 -> 6.5309524 | N86: =I86*G86*(A86-B86) -> 0.025887574 | O86: =G86*(A86-B86) -> 82.840237 | P86: =(A86-B86)*(I_Cout_ss*$Q$2+C86) -> 165.68047 | Q86: =(A86-B86)*(I_Cout_ss*$R$2+C86) -> 31.065089
A87: =VINMAX -> 50 | B87: =VINMAX*((ROW()-10)/104) -> 37.019231 | C87: =IF(B87>=$H$2,IF($D$2="CC", $G$2, B87/$G$2), 0) -> 0 | D87: =B2 -> 703.33333 | E87: =MIN(D87/(A87-B87),$C$2) -> 54.182716 | F87: =I_Cout_ss+C87 -> 6.1538462 | G87: =IF($F$2="YES", F87, E87) -> 6.1538462 | H87: =G87-C87 -> 6.1538462 | I87: =(COUTMAX/1000000)*(B87-B86)/H87 -> 0.0003125 | J87: =J86+I87 -> 0.0240625 | K87: =J87*1000 -> 24.0625 | L87: =H87/G87 -> 1 | M87: =1/COUTMAX*(E87/2-C87)*1000 -> 6.7728395 | N87: =I87*G87*(A87-B87) -> 0.024963018 | O87: =G87*(A87-B87) -> 79.881657 | P87: =(A87-B87)*(I_Cout_ss*$Q$2+C87) -> 159.76331 | Q87: =(A87-B87)*(I_Cout_ss*$R$2+C87) -> 29.955621
A88: =VINMAX -> 50 | B88: =VINMAX*((ROW()-10)/104) -> 37.5 | C88: =IF(B88>=$H$2,IF($D$2="CC", $G$2, B88/$G$2), 0) -> 0 | D88: =B2 -> 703.33333 | E88: =MIN(D88/(A88-B88),$C$2) -> 56.266667 | F88: =I_Cout_ss+C88 -> 6.1538462 | G88: =IF($F$2="YES", F88, E88) -> 6.1538462 | H88: =G88-C88 -> 6.1538462 | I88: =(COUTMAX/1000000)*(B88-B87)/H88 -> 0.0003125 | J88: =J87+I88 -> 0.024375 | K88: =J88*1000 -> 24.375 | L88: =H88/G88 -> 1 | M88: =1/COUTMAX*(E88/2-C88)*1000 -> 7.0333333 | N88: =I88*G88*(A88-B88) -> 0.024038462 | O88: =G88*(A88-B88) -> 76.923077 | P88: =(A88-B88)*(I_Cout_ss*$Q$2+C88) -> 153.84615 | Q88: =(A88-B88)*(I_Cout_ss*$R$2+C88) -> 28.846154
A89: =VINMAX -> 50 | B89: =VINMAX*((ROW()-10)/104) -> 37.980769 | C89: =IF(B89>=$H$2,IF($D$2="CC", $G$2, B89/$G$2), 0) -> 0 | D89: =B2 -> 703.33333 | E89: =MIN(D89/(A89-B89),$C$2) -> 58.517333 | F89: =I_Cout_ss+C89 -> 6.1538462 | G89: =IF($F$2="YES", F89, E89) -> 6.1538462 | H89: =G89-C89 -> 6.1538462 | I89: =(COUTMAX/1000000)*(B89-B88)/H89 -> 0.0003125 | J89: =J88+I89 -> 0.0246875 | K89: =J89*1000 -> 24.6875 | L89: =H89/G89 -> 1 | M89: =1/COUTMAX*(E89/2-C89)*1000 -> 7.3146667 | N89: =I89*G89*(A89-B89) -> 0.023113905 | O89: =G89*(A89-B89) -> 73.964497 | P89: =(A89-B89)*(I_Cout_ss*$Q$2+C89) -> 147.92899 | Q89: =(A89-B89)*(I_Cout_ss*$R$2+C89) -> 27.736686
A90: =VINMAX -> 50 | B90: =VINMAX*((ROW()-10)/104) -> 38.461538 | C90: =IF(B90>=$H$2,IF($D$2="CC", $G$2, B90/$G$2), 0) -> 0 | D90: =B2 -> 703.33333 | E90: =MIN(D90/(A90-B90),$C$2) -> 60.955556 | F90: =I_Cout_ss+C90 -> 6.1538462 | G90: =IF($F$2="YES", F90, E90) -> 6.1538462 | H90: =G90-C90 -> 6.1538462 | I90: =(COUTMAX/1000000)*(B90-B89)/H90 -> 0.0003125 | J90: =J89+I90 -> 0.025 | K90: =J90*1000 -> 25 | L90: =H90/G90 -> 1 | M90: =1/COUTMAX*(E90/2-C90)*1000 -> 7.6194444 | N90: =I90*G90*(A90-B90) -> 0.022189349 | O90: =G90*(A90-B90) -> 71.005917 | P90: =(A90-B90)*(I_Cout_ss*$Q$2+C90) -> 142.01183 | Q90: =(A90-B90)*(I_Cout_ss*$R$2+C90) -> 26.627219
A91: =VINMAX -> 50 | B91: =VINMAX*((ROW()-10)/104) -> 38.942308 | C91: =IF(B91>=$H$2,IF($D$2="CC", $G$2, B91/$G$2), 0) -> 0 | D91: =B2 -> 703.33333 | E91: =MIN(D91/(A91-B91),$C$2) -> 63.605797 | F91: =I_Cout_ss+C91 -> 6.1538462 | G91: =IF($F$2="YES", F91, E91) -> 6.1538462 | H91: =G91-C91 -> 6.1538462 | I91: =(COUTMAX/1000000)*(B91-B90)/H91 -> 0.0003125 | J91: =J90+I91 -> 0.0253125 | K91: =J91*1000 -> 25.3125 | L91: =H91/G91 -> 1 | M91: =1/COUTMAX*(E91/2-C91)*1000 -> 7.9507246 | N91: =I91*G91*(A91-B91) -> 0.021264793 | O91: =G91*(A91-B91) -> 68.047337 | P91: =(A91-B91)*(I_Cout_ss*$Q$2+C91) -> 136.09467 | Q91: =(A91-B91)*(I_Cout_ss*$R$2+C91) -> 25.517751
A92: =VINMAX -> 50 | B92: =VINMAX*((ROW()-10)/104) -> 39.423077 | C92: =IF(B92>=$H$2,IF($D$2="CC", $G$2, B92/$G$2), 0) -> 0 | D92: =B2 -> 703.33333 | E92: =MIN(D92/(A92-B92),$C$2) -> 66.49697 | F92: =I_Cout_ss+C92 -> 6.1538462 | G92: =IF($F$2="YES", F92, E92) -> 6.1538462 | H92: =G92-C92 -> 6.1538462 | I92: =(COUTMAX/1000000)*(B92-B91)/H92 -> 0.0003125 | J92: =J91+I92 -> 0.025625 | K92: =J92*1000 -> 25.625 | L92: =H92/G92 -> 1 | M92: =1/COUTMAX*(E92/2-C92)*1000 -> 8.3121212 | N92: =I92*G92*(A92-B92) -> 0.020340237 | O92: =G92*(A92-B92) -> 65.088757 | P92: =(A92-B92)*(I_Cout_ss*$Q$2+C92) -> 130.17751 | Q92: =(A92-B92)*(I_Cout_ss*$R$2+C92) -> 24.408284
A93: =VINMAX -> 50 | B93: =VINMAX*((ROW()-10)/104) -> 39.903846 | C93: =IF(B93>=$H$2,IF($D$2="CC", $G$2, B93/$G$2), 0) -> 0 | D93: =B2 -> 703.33333 | E93: =MIN(D93/(A93-B93),$C$2) -> 69.663492 | F93: =I_Cout_ss+C93 -> 6.1538462 | G93: =IF($F$2="YES", F93, E93) -> 6.1538462 | H93: =G93-C93 -> 6.1538462 | I93: =(COUTMAX/1000000)*(B93-B92)/H93 -> 0.0003125 | J93: =J92+I93 -> 0.0259375 | K93: =J93*1000 -> 25.9375 | L93: =H93/G93 -> 1 | M93: =1/COUTMAX*(E93/2-C93)*1000 -> 8.7079365 | N93: =I93*G93*(A93-B93) -> 0.01941568 | O93: =G93*(A93-B93) -> 62.130178 | P93: =(A93-B93)*(I_Cout_ss*$Q$2+C93) -> 124.26036 | Q93: =(A93-B93)*(I_Cout_ss*$R$2+C93) -> 23.298817
A94: =VINMAX -> 50 | B94: =VINMAX*((ROW()-10)/104) -> 40.384615 | C94: =IF(B94>=$H$2,IF($D$2="CC", $G$2, B94/$G$2), 0) -> 0 | D94: =B2 -> 703.33333 | E94: =MIN(D94/(A94-B94),$C$2) -> 73.146667 | F94: =I_Cout_ss+C94 -> 6.1538462 | G94: =IF($F$2="YES", F94, E94) -> 6.1538462 | H94: =G94-C94 -> 6.1538462 | I94: =(COUTMAX/1000000)*(B94-B93)/H94 -> 0.0003125 | J94: =J93+I94 -> 0.02625 | K94: =J94*1000 -> 26.25 | L94: =H94/G94 -> 1 | M94: =1/COUTMAX*(E94/2-C94)*1000 -> 9.1433333 | N94: =I94*G94*(A94-B94) -> 0.018491124 | O94: =G94*(A94-B94) -> 59.171598 | P94: =(A94-B94)*(I_Cout_ss*$Q$2+C94) -> 118.3432 | Q94: =(A94-B94)*(I_Cout_ss*$R$2+C94) -> 22.189349
A95: =VINMAX -> 50 | B95: =VINMAX*((ROW()-10)/104) -> 40.865385 | C95: =IF(B95>=$H$2,IF($D$2="CC", $G$2, B95/$G$2), 0) -> 0 | D95: =B2 -> 703.33333 | E95: =MIN(D95/(A95-B95),$C$2) -> 76.996491 | F95: =I_Cout_ss+C95 -> 6.1538462 | G95: =IF($F$2="YES", F95, E95) -> 6.1538462 | H95: =G95-C95 -> 6.1538462 | I95: =(COUTMAX/1000000)*(B95-B94)/H95 -> 0.0003125 | J95: =J94+I95 -> 0.0265625 | K95: =J95*1000 -> 26.5625 | L95: =H95/G95 -> 1 | M95: =1/COUTMAX*(E95/2-C95)*1000 -> 9.6245614 | N95: =I95*G95*(A95-B95) -> 0.017566568 | O95: =G95*(A95-B95) -> 56.213018 | P95: =(A95-B95)*(I_Cout_ss*$Q$2+C95) -> 112.42604 | Q95: =(A95-B95)*(I_Cout_ss*$R$2+C95) -> 21.079882
A96: =VINMAX -> 50 | B96: =VINMAX*((ROW()-10)/104) -> 41.346154 | C96: =IF(B96>=$H$2,IF($D$2="CC", $G$2, B96/$G$2), 0) -> 0 | D96: =B2 -> 703.33333 | E96: =MIN(D96/(A96-B96),$C$2) -> 81.274074 | F96: =I_Cout_ss+C96 -> 6.1538462 | G96: =IF($F$2="YES", F96, E96) -> 6.1538462 | H96: =G96-C96 -> 6.1538462 | I96: =(COUTMAX/1000000)*(B96-B95)/H96 -> 0.0003125 | J96: =J95+I96 -> 0.026875 | K96: =J96*1000 -> 26.875 | L96: =H96/G96 -> 1 | M96: =1/COUTMAX*(E96/2-C96)*1000 -> 10.159259 | N96: =I96*G96*(A96-B96) -> 0.016642012 | O96: =G96*(A96-B96) -> 53.254438 | P96: =(A96-B96)*(I_Cout_ss*$Q$2+C96) -> 106.50888 | Q96: =(A96-B96)*(I_Cout_ss*$R$2+C96) -> 19.970414
A97: =VINMAX -> 50 | B97: =VINMAX*((ROW()-10)/104) -> 41.826923 | C97: =IF(B97>=$H$2,IF($D$2="CC", $G$2, B97/$G$2), 0) -> 0 | D97: =B2 -> 703.33333 | E97: =MIN(D97/(A97-B97),$C$2) -> 86.054902 | F97: =I_Cout_ss+C97 -> 6.1538462 | G97: =IF($F$2="YES", F97, E97) -> 6.1538462 | H97: =G97-C97 -> 6.1538462 | I97: =(COUTMAX/1000000)*(B97-B96)/H97 -> 0.0003125 | J97: =J96+I97 -> 0.0271875 | K97: =J97*1000 -> 27.1875 | L97: =H97/G97 -> 1 | M97: =1/COUTMAX*(E97/2-C97)*1000 -> 10.756863 | N97: =I97*G97*(A97-B97) -> 0.015717456 | O97: =G97*(A97-B97) -> 50.295858 | P97: =(A97-B97)*(I_Cout_ss*$Q$2+C97) -> 100.59172 | Q97: =(A97-B97)*(I_Cout_ss*$R$2+C97) -> 18.860947
A98: =VINMAX -> 50 | B98: =VINMAX*((ROW()-10)/104) -> 42.307692 | C98: =IF(B98>=$H$2,IF($D$2="CC", $G$2, B98/$G$2), 0) -> 0 | D98: =B2 -> 703.33333 | E98: =MIN(D98/(A98-B98),$C$2) -> 86.666667 | F98: =I_Cout_ss+C98 -> 6.1538462 | G98: =IF($F$2="YES", F98, E98) -> 6.1538462 | H98: =G98-C98 -> 6.1538462 | I98: =(COUTMAX/1000000)*(B98-B97)/H98 -> 0.0003125 | J98: =J97+I98 -> 0.0275 | K98: =J98*1000 -> 27.5 | L98: =H98/G98 -> 1 | M98: =1/COUTMAX*(E98/2-C98)*1000 -> 10.833333 | N98: =I98*G98*(A98-B98) -> 0.014792899 | O98: =G98*(A98-B98) -> 47.337278 | P98: =(A98-B98)*(I_Cout_ss*$Q$2+C98) -> 94.674556 | Q98: =(A98-B98)*(I_Cout_ss*$R$2+C98) -> 17.751479
A99: =VINMAX -> 50 | B99: =VINMAX*((ROW()-10)/104) -> 42.788462 | C99: =IF(B99>=$H$2,IF($D$2="CC", $G$2, B99/$G$2), 0) -> 0 | D99: =B2 -> 703.33333 | E99: =MIN(D99/(A99-B99),$C$2) -> 86.666667 | F99: =I_Cout_ss+C99 -> 6.1538462 | G99: =IF($F$2="YES", F99, E99) -> 6.1538462 | H99: =G99-C99 -> 6.1538462 | I99: =(COUTMAX/1000000)*(B99-B98)/H99 -> 0.0003125 | J99: =J98+I99 -> 0.0278125 | K99: =J99*1000 -> 27.8125 | L99: =H99/G99 -> 1 | M99: =1/COUTMAX*(E99/2-C99)*1000 -> 10.833333 | N99: =I99*G99*(A99-B99) -> 0.013868343 | O99: =G99*(A99-B99) -> 44.378698 | P99: =(A99-B99)*(I_Cout_ss*$Q$2+C99) -> 88.757396 | Q99: =(A99-B99)*(I_Cout_ss*$R$2+C99) -> 16.642012
A100: =VINMAX -> 50 | B100: =VINMAX*((ROW()-10)/104) -> 43.269231 | C100: =IF(B100>=$H$2,IF($D$2="CC", $G$2, B100/$G$2), 0) -> 0 | D100: =B2 -> 703.33333 | E100: =MIN(D100/(A100-B100),$C$2) -> 86.666667 | F100: =I_Cout_ss+C100 -> 6.1538462 | G100: =IF($F$2="YES", F100, E100) -> 6.1538462 | H100: =G100-C100 -> 6.1538462 | I100: =(COUTMAX/1000000)*(B100-B99)/H100 -> 0.0003125 | J100: =J99+I100 -> 0.028125 | K100: =J100*1000 -> 28.125 | L100: =H100/G100 -> 1 | M100: =1/COUTMAX*(E100/2-C100)*1000 -> 10.833333 | N100: =I100*G100*(A100-B100) -> 0.012943787 | O100: =G100*(A100-B100) -> 41.420118 | P100: =(A100-B100)*(I_Cout_ss*$Q$2+C100) -> 82.840237 | Q100: =(A100-B100)*(I_Cout_ss*$R$2+C100) -> 15.532544
A101: =VINMAX -> 50 | B101: =VINMAX*((ROW()-10)/104) -> 43.75 | C101: =IF(B101>=$H$2,IF($D$2="CC", $G$2, B101/$G$2), 0) -> 0 | D101: =B2 -> 703.33333 | E101: =MIN(D101/(A101-B101),$C$2) -> 86.666667 | F101: =I_Cout_ss+C101 -> 6.1538462 | G101: =IF($F$2="YES", F101, E101) -> 6.1538462 | H101: =G101-C101 -> 6.1538462 | I101: =(COUTMAX/1000000)*(B101-B100)/H101 -> 0.0003125 | J101: =J100+I101 -> 0.0284375 | K101: =J101*1000 -> 28.4375 | L101: =H101/G101 -> 1 | M101: =1/COUTMAX*(E101/2-C101)*1000 -> 10.833333 | N101: =I101*G101*(A101-B101) -> 0.012019231 | O101: =G101*(A101-B101) -> 38.461538 | P101: =(A101-B101)*(I_Cout_ss*$Q$2+C101) -> 76.923077 | Q101: =(A101-B101)*(I_Cout_ss*$R$2+C101) -> 14.423077
...

Sheet SOA
C2: Look Up | H2: I = a * t^m
B3: 100us | C3: 1ms | D3: 10ms | E3: 100ms | F3: 1s/DC | H3: a = iSOA1/tSOA1^m
A4: Final SOA | B4: ='Design Calculator'!AN58 -> 300 | C4: ='Design Calculator'!$AN$59 -> 81 | D4: ='Design Calculator'!$AN$60 -> 18 | E4: =IF('Design Calculator'!$AN$61 = "NA", F4, 'Design Calculator'!$AN$61) -> 6.3 | F4: ='Design Calculator'!AN62 -> 4.5 | H4: m = log(iSOA1/iSOA2)/log(tSOA1/tSOA2)
B7: SOA Check - Based on Timer | G7: SOA Predictor - dv/dt start-up
B8: time | C8: =IF('Design Calculator'!F73="No", 'Design Calculator'!$F$79,'Design Calculator'!F92) -> 0.52 | D8: ms | G8: time | H8: =Equations!F60 -> 16.09375
B9: Voltage | C9: =VINMAX -> 50 | D9: V | G9: Voltage | H9: =VINMAX -> 50
B10: Lower time | C10: =IF(C8<10, IF(C8<1, 0.1, 1), IF(C8<100, 10, 100)) -> 0.1 | D10: ms | G10: Lower time | H10: =IF(H8<10, IF(H8<1, 0.1, 1), IF(H8<100, 10, 100)) -> 10
B11: Lower time (adjusted) | C11: =IF('Design Calculator'!F61="NA", MIN(SOA!C10,1),SOA!C10) -> 0.1 | G11: Lower time (adjusted) | H11: =IF('Design Calculator'!F61="NA", MIN(SOA!H10,1),SOA!H10) -> 10
B12: Higher timer | C12: =C10*10 -> 1 | D12: ms | G12: Higher time | H12: =H10*10 -> 100
B13: Higher time (adjusted) | C13: =IF('Design Calculator'!F62="NA", MIN(SOA!C12,10),SOA!C12) -> 1 | G13: Higher time (adjusted) | H13: =IF('Design Calculator'!F62="NA", MIN(SOA!H12,10),SOA!H12) -> 100
B14: I (lower time) | C14: =IF(C10=0.1, B4, IF(C10=1, C4, IF(C10=10, D4, E4))) -> 300 | D14: A | G14: I (lower time) | H14: =IF(H11=0.1, B4, IF(H11=1, C4, IF(H11=10, D4, E4))) -> 18
B15: I (higher time) | C15: =IF(C12=1000, F4, IF(C12=1, C4, IF(C12=10, D4, E4))) -> 81 | D15: A | G15: I (higher time) | H15: =IF(H13=1000, F4, IF(H13=1, C4, IF(H13=10, D4, E4))) -> 6.3
B17: Assuming Power vs time is linear on a log-log plot | G17: Assuming Power vs time is linear on a log-log plot
B18: a | C18: =C14/C11^C19 -> 81 | G18: a | H18: =H14/H11^H19 -> 51.428571
B19: m | C19: =LOG(C14/C15)/LOG(C11/C13) -> -0.56863624 | G19: m | H19: =IF(H14=H15,0.000000000001,LOG(H14/H15)/LOG(H11/H13)) -> -0.45593196 | I19: <-- Cannot plot zero on a log graph. If slope ~=0, then use 1e-12 as value
B20: Extr. I | C20: =C18*C8^C19 -> 117.48321 | D20: A | G20: Extr. I | H20: =H18*H8^H19 -> 14.489415
B22: Interpolated Power= | C22: =C20*C9 -> 5874.1606 | G22: Interpolated Power= | H22: =H20*H9 -> 724.47077
G24: board hot? | H24: ='Design Calculator'!F81 -> No
B25: Derating factor = | C25: =(TJMAX-TJ)/(TJMAX-25) -> 0.24803765 | G25: Temp for derating | H25: =IF(H24="Yes", TJ,TAMB) -> 85
B26: Max Power with Temp Derating = | C26: =IF((C22*C25)<0,0.000000001,C22*C25) -> 1457.013 | D26: W
G27: Derating factor = | H27: =(TJMAX-H25)/(TJMAX-25) -> 0.85882353
G28: Max Power with Temp Derating = | H28: =IF((H22*H27)<0,0.000000001,H22*H27) -> 622.19254
B29: SOA Coefficients
C30: 0.1 to 1 ms | D30: 1 to 10ms | E30: 10ms to 100 ms | F30: 100 ms to 1s
B31: t1 | C31: 0.1 | D31: 1 | E31: 10 | F31: 100
B32: t2 | C32: 1 | D32: 10 | E32: 100 | F32: 1000
B33: a | C33: =B4/(C31^C34) -> 81 | D33: =C4/(D31^D34) -> 81 | E33: =IF('Design Calculator'!F62="NA",D33,D4/(E31^E34)) -> 51.428571 | F33: =IF('Design Calculator'!F62="NA", E33, E4/(F31^F34)) -> 12.348
B34: m | C34: =LOG(B4/C4)/LOG(C31/C32) -> -0.56863624 | D34: =LOG(C4/D4)/LOG(D31/D32) -> -0.65321251 | E34: =IF('Design Calculator'!F62="NA", D34, LOG(D4/E4)/LOG(E31/E32)) -> -0.45593196 | F34: =IF('Design Calculator'!F62="NA",E34,LOG(E4/F4)/LOG(F31/F32)) -> -0.14612804

Sheet dv_dt_recommendations
C5: Key Equations for SOA margin estimate:
C7: 1) Get total Energy = 1/2 CV^2 + E_load (t_worksheet) * t_start / t_ worksheet
C8: note: t_worksheet is the start time from the start-up worksheet. E_load = Total Energy @ Start-up - 1/2CV^2
C10: 2) Get peak power: 4 Possible points with peak power
C11: a) At Vin = 0 [mainly if there is no load or constant current load that starts at Vout = 0=
C12: b) At Vin = Load start [ constant current=
C13: c) When derivative of power = 0 [Peak, applies to resistive loads only=
D14: P = (I_cap + Vout/R ) * (Vin - Vout) = Icap * Vin - Icap * Vout +Vin * Vout / R - Vout^2 / R
D15: => dP/dVout = -Icap + Vin/R -2Vout /R ; Zero when Vout = -R*I_cap / 2 + Vin / 2
D18: Copied Inputs
D19: Temp_start_up | E19: =SOA!H25 -> 85
D20: SOA margin target | E20: 1.5 | I20: SOA Coefficients
D21: Cap Energy (J) | E21: =1/2*COUTMAX*VINMAX^2*0.000001 -> 5 | J21: 0.1 to 1 ms | K21: 1 to 10ms | L21: 10ms to 100 ms | M21: 100 ms to 1s
D22: E_load (t_worksheet) (J) | E22: =MAX(Equations!F58-E21,0) -> 0 | I22: t1 | J22: 0.1 | K22: 1 | L22: 10 | M22: 100
D23: t_worksheet (ms) | E23: =Equations!F57 -> 32.5 | I23: t2 | J23: 1 | K23: 10 | L23: 100 | M23: 1000
I24: a | J24: =SOA!C33 -> 81 | K24: =SOA!D33 -> 81 | L24: =SOA!E33 -> 51.428571 | M24: =SOA!F33 -> 12.348
D25: Load Turn-On Threshold | E25: ='Design Calculator'!F70 -> 0 | I25: m | J25: =SOA!C34 -> -0.56863624 | K25: =SOA!D34 -> -0.65321251 | L25: =SOA!E34 -> -0.45593196 | M25: =SOA!F34 -> -0.14612804
D26: Startup Load Type | E26: ='Design Calculator'!F71 -> Constant Current
D27: Startup Load Value | E27: ='Design Calculator'!F72 -> 0 | I27: Initial | J27: Final
G28: max slew rate | I28: =SUM(E58:X58) -> 2.1995769 | J28: =IF(I28=0, "NA", I28/AVERAGE(1, E32)) -> 2.4648433
D29: Upper bound Slew Rate (4ms start-up) (V/ms) | E29: =12/1 -> 12 | G29: min slew rate | I29: =SUM(E59:X59) -> 0.12 | J29: =IF(I29=0, "NA", I29*AVERAGE(1,E32)) -> 0.1070856
D30: Min Slew Rate (400 ms start - up) (V/ms) | E30: 0.12
D31: # of points | E31: 20
D32: mult per point | E32: =(E30/E29)^(1/(E31-1)) -> 0.78475997
E34: 1 | F34: 2 | G34: 3 | H34: 4 | I34: 5 | J34: 6 | K34: 7 | L34: 8 | M34: 9 | N34: 10 | O34: 11 | P34: 12 | Q34: 13 | R34: 14 | S34: 15 | T34: 16 | U34: 17 | V34: 18 | W34: 19 | X34: 20
D35: slew rate (V/ms) | E35: =E29 -> 12 | F35: =E35*$E$32 -> 9.4171196 | G35: =F35*$E$32 -> 7.3901785 | H35: =G35*$E$32 -> 5.7995163 | I35: =H35*$E$32 -> 4.5512282 | J35: =I35*$E$32 -> 3.5716217 | K35: =J35*$E$32 -> 2.8028658 | L35: =K35*$E$32 -> 2.1995769 | M35: =L35*$E$32 -> 1.7261399 | ... X35: =W35*$E$32 -> 0.12
D36: t_start (ms) | E36: =VINMAX/E35 -> 4.1666667 | F36: =VINMAX/F35 -> 5.3094791 | G36: =VINMAX/G35 -> 6.7657364 | H36: =VINMAX/H35 -> 8.6214087 | I36: =VINMAX/I35 -> 10.986045 | J36: =VINMAX/J35 -> 13.999243 | K36: =VINMAX/K35 -> 17.838885 | L36: =VINMAX/L35 -> 22.731645 | ... X36: =VINMAX/X35 -> 416.66667
D37: I_cap (A) | E37: =E35*COUTMAX/1000 -> 48 | F37: =F35*COUTMAX/1000 -> 37.668479 | G37: =G35*COUTMAX/1000 -> 29.560714 | H37: =H35*COUTMAX/1000 -> 23.198065 | I37: =I35*COUTMAX/1000 -> 18.204913 | J37: =J35*COUTMAX/1000 -> 14.286487 | K37: =K35*COUTMAX/1000 -> 11.211463 | L37: =L35*COUTMAX/1000 -> 8.7983074 | ... X37: =X35*COUTMAX/1000 -> 0.48
D38: Total FET Energy (J) | E38: =$E$21+$E$22*E36/$E$23 -> 5 | F38: =$E$21+$E$22*F36/$E$23 -> 5 | G38: =$E$21+$E$22*G36/$E$23 -> 5 | H38: =$E$21+$E$22*H36/$E$23 -> 5 | I38: =$E$21+$E$22*I36/$E$23 -> 5 | J38: =$E$21+$E$22*J36/$E$23 -> 5 | K38: =$E$21+$E$22*K36/$E$23 -> 5 | L38: =$E$21+$E$22*L36/$E$23 -> 5 | ... X38: =$E$21+$E$22*X36/$E$23 -> 5
D39: Power (Vout= 0) , (W) | E39: =(E37+IF($E$26="Resistive",0,IF($E$25=0,$E$27,0)))*VINMAX -> 2400 | F39: =(F37+IF($E$26="Resistive",0,IF($E$25=0,$E$27,0)))*VINMAX -> 1883.4239 | G39: =(G37+IF($E$26="Resistive",0,IF($E$25=0,$E$27,0)))*VINMAX -> 1478.0357 | H39: =(H37+IF($E$26="Resistive",0,IF($E$25=0,$E$27,0)))*VINMAX -> 1159.9033 | I39: =(I37+IF($E$26="Resistive",0,IF($E$25=0,$E$27,0)))*VINMAX -> 910.24565 | J39: =(J37+IF($E$26="Resistive",0,IF($E$25=0,$E$27,0)))*VINMAX -> 714.32435 | K39: =(K37+IF($E$26="Resistive",0,IF($E$25=0,$E$27,0)))*VINMAX -> 560.57315 | L39: =(L37+IF($E$26="Resistive",0,IF($E$25=0,$E$27,0)))*VINMAX -> 439.91537 | ... X39: =(X37+IF($E$26="Resistive",0,IF($E$25=0,$E$27,0)))*VINMAX -> 24
D40: Power (load on), (W) | E40: =(E37+IF($E$26="Resistive", $E$25/$E$27,$E$27)) *(VINMAX-$E$25) -> 2400 | F40: =(F37+IF($E$26="Resistive", $E$25/$E$27,$E$27)) *(VINMAX-$E$25) -> 1883.4239 | G40: =(G37+IF($E$26="Resistive", $E$25/$E$27,$E$27)) *(VINMAX-$E$25) -> 1478.0357 | H40: =(H37+IF($E$26="Resistive", $E$25/$E$27,$E$27)) *(VINMAX-$E$25) -> 1159.9033 | I40: =(I37+IF($E$26="Resistive", $E$25/$E$27,$E$27)) *(VINMAX-$E$25) -> 910.24565 | J40: =(J37+IF($E$26="Resistive", $E$25/$E$27,$E$27)) *(VINMAX-$E$25) -> 714.32435 | K40: =(K37+IF($E$26="Resistive", $E$25/$E$27,$E$27)) *(VINMAX-$E$25) -> 560.57315 | L40: =(L37+IF($E$26="Resistive", $E$25/$E$27,$E$27)) *(VINMAX-$E$25) -> 439.91537 | ... X40: =(X37+IF($E$26="Resistive", $E$25/$E$27,$E$27)) *(VINMAX-$E$25) -> 24
D41: Vout (dP/dVout = 0) (V) | E41: =IF($E$26="Resistive", -$E$27*E37/2 + VINMAX/2, -1) -> -1 | F41: =IF($E$26="Resistive", -$E$27*F37/2 + VINMAX/2, -1) -> -1 | G41: =IF($E$26="Resistive", -$E$27*G37/2 + VINMAX/2, -1) -> -1 | H41: =IF($E$26="Resistive", -$E$27*H37/2 + VINMAX/2, -1) -> -1 | I41: =IF($E$26="Resistive", -$E$27*I37/2 + VINMAX/2, -1) -> -1 | J41: =IF($E$26="Resistive", -$E$27*J37/2 + VINMAX/2, -1) -> -1 | K41: =IF($E$26="Resistive", -$E$27*K37/2 + VINMAX/2, -1) -> -1 | L41: =IF($E$26="Resistive", -$E$27*L37/2 + VINMAX/2, -1) -> -1 | ... X41: =IF($E$26="Resistive", -$E$27*X37/2 + VINMAX/2, -1) -> -1
D42: Power (@ Vout above, if applicable) | E42: =IF(AND(E41<VINMAX, E41>$E$25), (VINMAX-E41)*(E37+E41/$E$27), 0) -> 0 | F42: =IF(AND(F41<VINMAX, F41>$E$25), (VINMAX-F41)*(F37+F41/$E$27), 0) -> 0 | G42: =IF(AND(G41<VINMAX, G41>$E$25), (VINMAX-G41)*(G37+G41/$E$27), 0) -> 0 | H42: =IF(AND(H41<VINMAX, H41>$E$25), (VINMAX-H41)*(H37+H41/$E$27), 0) -> 0 | I42: =IF(AND(I41<VINMAX, I41>$E$25), (VINMAX-I41)*(I37+I41/$E$27), 0) -> 0 | J42: =IF(AND(J41<VINMAX, J41>$E$25), (VINMAX-J41)*(J37+J41/$E$27), 0) -> 0 | K42: =IF(AND(K41<VINMAX, K41>$E$25), (VINMAX-K41)*(K37+K41/$E$27), 0) -> 0 | L42: =IF(AND(L41<VINMAX, L41>$E$25), (VINMAX-L41)*(L37+L41/$E$27), 0) -> 0 | ... X42: =IF(AND(X41<VINMAX, X41>$E$25), (VINMAX-X41)*(X37+X41/$E$27), 0) -> 0
D44: max power (W) | E44: =MAX(E39,E40,E42) -> 2400 | F44: =MAX(F39,F40,F42) -> 1883.4239 | G44: =MAX(G39,G40,G42) -> 1478.0357 | H44: =MAX(H39,H40,H42) -> 1159.9033 | I44: =MAX(I39,I40,I42) -> 910.24565 | J44: =MAX(J39,J40,J42) -> 714.32435 | K44: =MAX(K39,K40,K42) -> 560.57315 | L44: =MAX(L39,L40,L42) -> 439.91537 | ... X44: =MAX(X39,X40,X42) -> 24
D45: Equivalent time for SOA (ms) | E45: =E38/E44*1000 -> 2.0833333 | F45: =F38/F44*1000 -> 2.6547396 | G45: =G38/G44*1000 -> 3.3828682 | H45: =H38/H44*1000 -> 4.3107043 | I45: =I38/I44*1000 -> 5.4930227 | J45: =J38/J44*1000 -> 6.9996214 | K45: =K38/K44*1000 -> 8.9194425 | L45: =L38/L44*1000 -> 11.365822 | ... X45: =X38/X44*1000 -> 208.33333
D47: a | E47: =IF(E45<$J$23,$J$24,IF(E45<$K$23,$K$24,IF(E45<$L$23,$L$24,$M$24))) -> 81 | F47: =IF(F45<$J$23,$J$24,IF(F45<$K$23,$K$24,IF(F45<$L$23,$L$24,$M$24))) -> 81 | G47: =IF(G45<$J$23,$J$24,IF(G45<$K$23,$K$24,IF(G45<$L$23,$L$24,$M$24))) -> 81 | H47: =IF(H45<$J$23,$J$24,IF(H45<$K$23,$K$24,IF(H45<$L$23,$L$24,$M$24))) -> 81 | I47: =IF(I45<$J$23,$J$24,IF(I45<$K$23,$K$24,IF(I45<$L$23,$L$24,$M$24))) -> 81 | J47: =IF(J45<$J$23,$J$24,IF(J45<$K$23,$K$24,IF(J45<$L$23,$L$24,$M$24))) -> 81 | K47: =IF(K45<$J$23,$J$24,IF(K45<$K$23,$K$24,IF(K45<$L$23,$L$24,$M$24))) -> 81 | L47: =IF(L45<$J$23,$J$24,IF(L45<$K$23,$K$24,IF(L45<$L$23,$L$24,$M$24))) -> 51.428571 | ... X47: =IF(X45<$J$23,$J$24,IF(X45<$K$23,$K$24,IF(X45<$L$23,$L$24,$M$24))) -> 12.348
D48: m | E48: =IF(E45<$J$23,$J$25,IF(E45<$K$23,$K$25,IF(E45<$L$23,$L$25,$M$25))) -> -0.65321251 | F48: =IF(F45<$J$23,$J$25,IF(F45<$K$23,$K$25,IF(F45<$L$23,$L$25,$M$25))) -> -0.65321251 | G48: =IF(G45<$J$23,$J$25,IF(G45<$K$23,$K$25,IF(G45<$L$23,$L$25,$M$25))) -> -0.65321251 | H48: =IF(H45<$J$23,$J$25,IF(H45<$K$23,$K$25,IF(H45<$L$23,$L$25,$M$25))) -> -0.65321251 | I48: =IF(I45<$J$23,$J$25,IF(I45<$K$23,$K$25,IF(I45<$L$23,$L$25,$M$25))) -> -0.65321251 | J48: =IF(J45<$J$23,$J$25,IF(J45<$K$23,$K$25,IF(J45<$L$23,$L$25,$M$25))) -> -0.65321251 | K48: =IF(K45<$J$23,$J$25,IF(K45<$K$23,$K$25,IF(K45<$L$23,$L$25,$M$25))) -> -0.65321251 | L48: =IF(L45<$J$23,$J$25,IF(L45<$K$23,$K$25,IF(L45<$L$23,$L$25,$M$25))) -> -0.45593196 | ... X48: =IF(X45<$J$23,$J$25,IF(X45<$K$23,$K$25,IF(X45<$L$23,$L$25,$M$25))) -> -0.14612804
D50: Available SOA (W) | E50: =E47*E45^E48*VINMAX -> 2507.4819 | F50: =F47*F45^F48*VINMAX -> 2140.3195 | G50: =G47*G45^G48*VINMAX -> 1826.9194 | H50: =H47*H45^H48*VINMAX -> 1559.4095 | I50: =I47*I45^I48*VINMAX -> 1331.0702 | J50: =J47*J45^J48*VINMAX -> 1136.1659 | K50: =K47*K45^K48*VINMAX -> 969.8008 | L50: =L47*L45^L48*VINMAX -> 848.96991 | ... X50: =X47*X45^X48*VINMAX -> 282.96385
D51: Derated for Temp | E51: =E50*(TJMAX-$E$19)/(TJMAX - 25) -> 2153.4845 | F51: =F50*(TJMAX-$E$19)/(TJMAX - 25) -> 1838.1567 | G51: =G50*(TJMAX-$E$19)/(TJMAX - 25) -> 1569.0014 | H51: =H50*(TJMAX-$E$19)/(TJMAX - 25) -> 1339.2576 | I51: =I50*(TJMAX-$E$19)/(TJMAX - 25) -> 1143.1544 | J51: =J50*(TJMAX-$E$19)/(TJMAX - 25) -> 975.76601 | K51: =K50*(TJMAX-$E$19)/(TJMAX - 25) -> 832.88775 | L51: =L50*(TJMAX-$E$19)/(TJMAX - 25) -> 729.11533 | ... X51: =X50*(TJMAX-$E$19)/(TJMAX - 25) -> 243.01602
D52: SOA Margin | E52: =E51/E44 -> 0.8972852 | F52: =F51/F44 -> 0.97596546 | G52: =G51/G44 -> 1.061545 | H52: =H51/H44 -> 1.1546287 | I52: =I51/I44 -> 1.2558746 | J52: =J51/J44 -> 1.3659985 | K52: =K51/K44 -> 1.4857789 | L52: =L51/L44 -> 1.6573991 | ... X52: =X51/X44 -> 10.125667
D54: Pass? | E54: =IF(E52>$E$20, "Y", "N") -> N | F54: =IF(F52>$E$20, "Y", "N") -> N | G54: =IF(G52>$E$20, "Y", "N") -> N | H54: =IF(H52>$E$20, "Y", "N") -> N | I54: =IF(I52>$E$20, "Y", "N") -> N | J54: =IF(J52>$E$20, "Y", "N") -> N | K54: =IF(K52>$E$20, "Y", "N") -> N | L54: =IF(L52>$E$20, "Y", "N") -> Y | ... X54: =IF(X52>$E$20, "Y", "N") -> Y | Y54: N
D55: first yes | E55: =IF(E54="Y", 1, 0) -> 0 | F55: =IF(AND(F54="Y", E54="N"), 1, 0) -> 0 | G55: =IF(AND(G54="Y", F54="N"), 1, 0) -> 0 | H55: =IF(AND(H54="Y", G54="N"), 1, 0) -> 0 | I55: =IF(AND(I54="Y", H54="N"), 1, 0) -> 0 | J55: =IF(AND(J54="Y", I54="N"), 1, 0) -> 0 | K55: =IF(AND(K54="Y", J54="N"), 1, 0) -> 0 | L55: =IF(AND(L54="Y", K54="N"), 1, 0) -> 1 | M55: =IF(AND(M54="Y", L54="N"), 1, 0) -> 0 | ... X55: =IF(AND(X54="Y", W54="N"), 1, 0) -> 0
D56: 2nd yes | E56: 0 | F56: =IF(AND(F54="Y", G54="N"), 1, 0) -> 0 | G56: =IF(AND(G54="Y", H54="N"), 1, 0) -> 0 | H56: =IF(AND(H54="Y", I54="N"), 1, 0) -> 0 | I56: =IF(AND(I54="Y", J54="N"), 1, 0) -> 0 | J56: =IF(AND(J54="Y", K54="N"), 1, 0) -> 0 | K56: =IF(AND(K54="Y", L54="N"), 1, 0) -> 0 | L56: =IF(AND(L54="Y", M54="N"), 1, 0) -> 0 | M56: =IF(AND(M54="Y", N54="N"), 1, 0) -> 0 | ... X56: =IF(AND(X54="Y", Y54="N"), 1, 0) -> 1
D58: Mult 1 | E58: =E55*E35 -> 0 | F58: =F55*F35 -> 0 | G58: =G55*G35 -> 0 | H58: =H55*H35 -> 0 | I58: =I55*I35 -> 0 | J58: =J55*J35 -> 0 | K58: =K55*K35 -> 0 | L58: =L55*L35 -> 2.1995769 | ... X58: =X55*X35 -> 0
D59: mult2 | E59: =E35*E56 -> 0 | F59: =F35*F56 -> 0 | G59: =G35*G56 -> 0 | H59: =H35*H56 -> 0 | I59: =I35*I56 -> 0 | J59: =J35*J56 -> 0 | K59: =K35*K56 -> 0 | L59: =L35*L56 -> 0 | ... X59: =X35*X56 -> 0.12
